{"autoplayBgm":false,"autoplayBgs":false,"battleback1Name":"","battleback2Name":"","bgm":{"name":"","pan":0,"pitch":100,"volume":90},"bgs":{"name":"","pan":0,"pitch":100,"volume":90},"disableDashing":false,"displayName":"","encounterList":[],"encounterStep":30,"height":13,"note":"","parallaxLoopX":false,"parallaxLoopY":false,"parallaxName":"47-2","parallaxShow":true,"parallaxSx":0,"parallaxSy":0,"scrollType":0,"specifyBattleback":false,"tilesetId":1,"width":17,"data":[0,0,0,0,0,0,0,0,0,0,0,0,0,0,0,0,0,0,0,0,0,0,0,0,0,0,0,0,0,0,0,0,0,0,0,0,0,0,0,0,0,0,0,0,0,0,0,0,0,0,0,0,0,0,0,0,0,0,0,0,0,0,0,0,0,0,0,0,0,0,0,0,0,0,0,0,0,0,0,0,0,0,0,0,0,0,0,0,0,0,0,0,0,0,0,0,0,0,0,0,0,0,0,0,0,0,0,0,0,0,0,0,0,0,0,0,0,0,0,0,0,0,0,0,0,0,0,0,0,0,0,0,0,0,0,0,0,0,0,0,0,0,0,0,0,0,0,0,0,0,0,0,0,0,0,0,0,0,0,0,0,0,0,0,0,0,0,0,0,0,0,0,0,0,0,0,0,0,0,0,0,0,0,0,0,0,0,0,0,0,0,0,0,0,0,0,0,0,0,0,0,0,0,0,0,0,0,0,0,0,0,0,0,0,0,0,0,0,0,0,0,0,0,0,0,0,0,0,0,0,0,0,0,0,0,0,0,0,0,0,0,0,0,0,0,0,0,0,0,0,0,0,0,0,0,0,0,0,0,0,0,0,0,0,0,0,0,0,0,0,0,0,0,0,0,0,0,0,0,0,0,0,0,0,0,0,0,0,0,0,0,0,0,0,0,0,0,0,0,0,0,0,0,0,0,0,0,0,0,0,0,0,0,0,0,0,0,0,0,0,0,0,0,0,0,0,0,0,0,0,0,0,0,0,0,0,0,0,0,0,0,0,0,0,0,0,0,0,0,0,0,0,0,0,0,0,0,0,0,0,0,0,0,0,0,0,0,0,0,0,0,0,0,0,0,0,0,0,0,0,0,0,0,0,0,0,0,0,0,0,0,0,0,0,0,0,0,0,0,0,0,0,0,0,0,0,0,0,0,0,0,0,0,0,0,0,0,0,0,0,0,0,0,0,0,0,0,0,0,0,0,0,0,0,0,0,0,0,0,0,0,0,0,0,0,0,0,0,0,0,0,0,0,0,0,0,0,0,0,0,0,0,0,0,0,0,0,0,0,0,0,0,0,0,0,0,0,0,0,0,0,0,0,0,0,0,0,0,0,0,0,0,0,0,0,0,0,0,0,0,0,0,0,0,0,0,0,0,0,0,0,0,0,0,0,0,0,0,0,0,0,0,0,0,0,0,0,0,0,0,0,0,0,0,0,0,0,0,0,0,0,0,0,0,0,0,0,0,0,0,0,0,0,0,0,0,0,0,0,0,0,0,0,0,0,0,0,0,0,0,0,0,0,0,0,0,0,0,0,0,0,0,0,0,0,0,0,0,0,0,0,0,0,0,0,0,0,0,0,0,0,0,0,0,0,0,0,0,0,0,0,0,0,0,0,0,0,0,0,0,0,0,0,0,0,0,0,0,0,0,0,0,0,0,0,0,0,0,0,0,0,0,0,0,0,0,0,0,0,0,0,0,0,0,0,0,0,0,0,0,0,0,0,0,0,0,0,0,0,0,0,0,0,0,0,0,0,0,0,0,0,0,0,0,0,0,0,0,0,0,0,0,0,0,0,0,0,0,0,0,0,0,0,0,0,0,0,0,0,0,0,0,0,0,0,0,0,0,0,0,0,0,0,0,0,0,0,0,0,0,0,0,0,0,0,0,0,0,0,0,0,0,0,0,0,0,0,0,0,0,0,0,0,0,0,0,0,0,0,0,0,0,0,0,0,0,0,0,0,0,0,0,0,0,0,0,0,0,0,0,0,0,0,0,0,0,0,0,0,0,0,0,0,0,0,0,0,0,0,0,0,0,0,0,0,0,0,0,0,0,0,0,0,0,0,0,0,0,0,0,0,0,0,0,0,0,0,0,0,0,0,0,0,0,0,0,0,0,0,0,0,0,0,0,0,0,0,0,0,0,0,0,0,0,0,0,0,0,0,0,0,0,0,0,0,0,0,0,0,0,0,0,0,0,0,0,0,0,0,0,0,0,0,0,0,0,0,0,0,0,0,0,0,0,0,0,0,0,0,0,0,0,0,0,0,0,0,0,0,0,0,0,0,0,0,0,0,0,0,0,0,0,0,0,0,0,0,0,0,0,0,0,0,0,0,0,0,0,0,0,0,0,0,0,0,0,0,0,0,0,0,0,0,0,0,0,0,0,0,0,0,0,0,0,0,0,0,0,0,0,0,0,0,0,0,0,0,0,0,0,0,0,0,0,0,0,0,0,0,0,0,0,0,0,0,0,0,0,0,0,0,0,0,0,0,0,0,0,0,0,0,0,0,0,0,0,0,0,0,0,0,0,0,0,0,0,0,0,0,0,0,0,0,0,0,0,0,0,0,0,0,0,0,0,0,0,0,0,0,0,0,0,0,0,0,0,0,0,0,0,0,0,0,0,0,0,0,0,0,0,0,0,0,0,0,0,0,0,0,0,0,0,0,0,0,0,0,0,0,0,0,0,0,0,0,0,0,0,0,0,0,0,0,0,0,0,0,0,0,0,0,0,0,0,0,0,0,0,0,0,0,0,0,0,0,0,0,0,0,0,0,0,0,0,0,0,0,0,0,0,0,0,0,0,0,0,0,0,0,0,0,0,0,0,0,0,0,0,0,0,0,0,0,0,0,0,0,0,0,0,0,0,0,0,0,0,0,0,0,0,0,0,0,0,0,0,0,0,0,0,0,0,0,0,0,0,0,0,0,0,0,0,0,0,0,0,0,0,0,0,0,0,0,0,0,0,0,0,0,0,0,0,0,0,0,0,0,0,0,0,0,0,0,0,0,0,0,0,0,0,0,0,0,0,0,0,0,0,0,0,0,0,0,0,0,0,0,0,0,0,0,0,0,0,0,0,0,0,0,0,0,0,0,0,0,0,0,0,0,0,0,0,0,0,0,0,0,0,0,0,0,0,0,0,0,0,0,0,0,0,0,0,0,0,0,0,0,0,0,0,0,0,0,0,0,0,0,0,0,0,0,0,0,0,0,0],"events":[null,{"id":1,"name":"EV001","note":"","pages":[{"conditions":{"actorId":1,"actorValid":false,"itemId":1,"itemValid":false,"selfSwitchCh":"A","selfSwitchValid":false,"switch1Id":1,"switch1Valid":false,"switch2Id":1,"switch2Valid":false,"variableId":1,"variableValid":true,"variableValue":1019},"directionFix":false,"image":{"characterIndex":0,"characterName":"","direction":2,"pattern":0,"tileId":0},"list":[{"code":117,"indent":0,"parameters":[18]},{"code":230,"indent":0,"parameters":[40]},{"code":356,"indent":0,"parameters":["NameBoxSet Sara"]},{"code":101,"indent":0,"parameters":["",0,0,2]},{"code":401,"indent":0,"parameters":["\"Anf... pant...!!\""]},{"code":250,"indent":0,"parameters":[{"name":"feed1","volume":90,"pitch":100,"pan":0}]},{"code":225,"indent":0,"parameters":[7,7,30,false]},{"code":101,"indent":0,"parameters":["",0,0,2]},{"code":401,"indent":0,"parameters":["\\.\"No...\""]},{"code":250,"indent":0,"parameters":[{"name":"Accent21-1","volume":90,"pitch":100,"pan":0}]},{"code":224,"indent":0,"parameters":[[255,255,255,170],60,false]},{"code":111,"indent":0,"parameters":[0,642,0]},{"code":356,"indent":1,"parameters":["NameBoxReset "]},{"code":101,"indent":1,"parameters":["",0,0,2]},{"code":401,"indent":1,"parameters":["\\.\\C[3]Il corpo di Alice \u00e8 stato del tutto ripulito."]},{"code":0,"indent":1,"parameters":[]},{"code":411,"indent":0,"parameters":[]},{"code":356,"indent":1,"parameters":["NameBoxReset "]},{"code":101,"indent":1,"parameters":["",0,0,2]},{"code":401,"indent":1,"parameters":["\\.\\C[3]Il corpo di Reko \u00e8 stato del tutto ripulito."]},{"code":0,"indent":1,"parameters":[]},{"code":412,"indent":0,"parameters":[]},{"code":241,"indent":0,"parameters":[{"name":"Horror-ginen_loop","volume":90,"pitch":100,"pan":0}]},{"code":250,"indent":0,"parameters":[{"name":"feed1","volume":90,"pitch":100,"pan":0}]},{"code":225,"indent":0,"parameters":[7,7,30,false]},{"code":356,"indent":0,"parameters":["NameBoxSet Sara"]},{"code":101,"indent":0,"parameters":["",0,0,2]},{"code":401,"indent":0,"parameters":["\\.\"State scherzando...!!\""]},{"code":250,"indent":0,"parameters":[{"name":"feed1","volume":90,"pitch":100,"pan":0}]},{"code":225,"indent":0,"parameters":[7,7,30,false]},{"code":101,"indent":0,"parameters":["",0,0,2]},{"code":401,"indent":0,"parameters":["\\.\"Perch\u00e9...?! No...!!\""]},{"code":101,"indent":0,"parameters":["",0,0,2]},{"code":401,"indent":0,"parameters":["\\.\\sp[20]\"Ora io...\""]},{"code":101,"indent":0,"parameters":["",0,0,2]},{"code":401,"indent":0,"parameters":["\\.\\sp[15]\"Cosa... faccio...\""]},{"code":231,"indent":0,"parameters":[31,"cara15-1",1,0,408,312,100,100,0,0]},{"code":232,"indent":0,"parameters":[31,0,1,0,408,312,100,100,255,0,30,true]},{"code":242,"indent":0,"parameters":[1]},{"code":250,"indent":0,"parameters":[{"name":"Accent21-1","volume":90,"pitch":100,"pan":0}]},{"code":224,"indent":0,"parameters":[[255,255,255,170],60,false]},{"code":356,"indent":0,"parameters":["NameBoxSet Mina"]},{"code":101,"indent":0,"parameters":["",0,0,2]},{"code":401,"indent":0,"parameters":["\\.\"... Signorina Sara.\""]},{"code":356,"indent":0,"parameters":["NameBoxSet Sara"]},{"code":101,"indent":0,"parameters":["",0,0,2]},{"code":401,"indent":0,"parameters":["\\.\\sp[15]\"... Mina...\""]},{"code":231,"indent":0,"parameters":[31,"cara15-2",1,0,408,312,100,100,255,0]},{"code":356,"indent":0,"parameters":["NameBoxSet Mina"]},{"code":101,"indent":0,"parameters":["",0,0,2]},{"code":401,"indent":0,"parameters":["\\.\"Ho appena finito le pulizie...\""]},{"code":231,"indent":0,"parameters":[31,"cara15-1",1,0,408,312,100,100,255,0]},{"code":101,"indent":0,"parameters":["",0,0,2]},{"code":401,"indent":0,"parameters":["\\.\"Certo... Ho anche trasportato attentamente i corpi.\""]},{"code":231,"indent":0,"parameters":[30,"1an",1,0,408,312,2000,2000,0,0]},{"code":232,"indent":0,"parameters":[30,0,1,0,408,312,2000,2000,255,0,60,false]},{"code":356,"indent":0,"parameters":["NameBoxSet Sara"]},{"code":101,"indent":0,"parameters":["",0,0,2]},{"code":401,"indent":0,"parameters":["\\.\"...\""]},{"code":245,"indent":0,"parameters":[{"name":"ghost_sigh","volume":90,"pitch":100,"pan":0}]},{"code":101,"indent":0,"parameters":["",0,0,2]},{"code":401,"indent":0,"parameters":["\\.\\C[4](... Forse \u00e8 la mia ultima possibilit\u00e0.)"]},{"code":102,"indent":0,"parameters":[["Rinuncia ai gettoni","Inganna Mina"],-1,-1,2,0]},{"code":402,"indent":0,"parameters":[0,"Rinuncia ai gettoni"]},{"code":230,"indent":1,"parameters":[10]},{"code":122,"indent":1,"parameters":[288,288,0,0,0]},{"code":245,"indent":1,"parameters":[{"name":"","volume":90,"pitch":100,"pan":0}]},{"code":235,"indent":1,"parameters":[30]},{"code":250,"indent":1,"parameters":[{"name":"Accent21-1","volume":90,"pitch":100,"pan":0}]},{"code":224,"indent":1,"parameters":[[255,255,255,170],60,false]},{"code":356,"indent":1,"parameters":["NameBoxSet Sara"]},{"code":101,"indent":1,"parameters":["",0,0,2]},{"code":401,"indent":1,"parameters":["\"... E' tutto finito... vero...?\""]},{"code":231,"indent":1,"parameters":[31,"cara15-3",1,0,408,312,100,100,255,0]},{"code":356,"indent":1,"parameters":["NameBoxSet Mina"]},{"code":101,"indent":1,"parameters":["",0,0,2]},{"code":401,"indent":1,"parameters":["\\.\"...?\""]},{"code":250,"indent":1,"parameters":[{"name":"feed1","volume":90,"pitch":100,"pan":0}]},{"code":225,"indent":1,"parameters":[7,7,30,false]},{"code":356,"indent":1,"parameters":["NameBoxSet Sara"]},{"code":101,"indent":1,"parameters":["",0,0,2]},{"code":401,"indent":1,"parameters":["\\.\"Ehehe... hahaha...\""]},{"code":231,"indent":1,"parameters":[31,"cara15-1",1,0,408,312,100,100,255,0]},{"code":250,"indent":1,"parameters":[{"name":"feed1","volume":90,"pitch":100,"pan":0}]},{"code":225,"indent":1,"parameters":[7,7,30,false]},{"code":356,"indent":1,"parameters":["NameBoxSet Mina"]},{"code":101,"indent":1,"parameters":["",0,0,2]},{"code":401,"indent":1,"parameters":["\\.\"S-Signorina Sara...?"]},{"code":401,"indent":1,"parameters":["Si sente beneeee?\""]},{"code":356,"indent":1,"parameters":["NameBoxSet Sara"]},{"code":101,"indent":1,"parameters":["",0,0,2]},{"code":401,"indent":1,"parameters":["\\.\"Un rapitore che si preoccupa per me...? Hah...\""]},{"code":231,"indent":1,"parameters":[31,"cara15-8",1,0,408,312,100,100,255,0]},{"code":250,"indent":1,"parameters":[{"name":"feed1","volume":90,"pitch":100,"pan":0}]},{"code":225,"indent":1,"parameters":[7,7,30,false]},{"code":356,"indent":1,"parameters":["NameBoxSet Mina"]},{"code":101,"indent":1,"parameters":["",0,0,2]},{"code":401,"indent":1,"parameters":["\\.\"Aah...\""]},{"code":356,"indent":1,"parameters":["NameBoxSet Sara"]},{"code":101,"indent":1,"parameters":["",0,0,2]},{"code":401,"indent":1,"parameters":["\\.\"Mina... E' divertente?\""]},{"code":101,"indent":1,"parameters":["",0,0,2]},{"code":401,"indent":1,"parameters":["\\.\"Giocare con noi usando sciocchezze come"]},{"code":401,"indent":1,"parameters":["gettoni e Clear Chip...\""]},{"code":250,"indent":1,"parameters":[{"name":"sceneswitch2","volume":90,"pitch":100,"pan":0}]},{"code":224,"indent":1,"parameters":[[255,255,255,170],60,false]},{"code":101,"indent":1,"parameters":["",0,0,2]},{"code":401,"indent":1,"parameters":["\\.\"E se c'\u00e8 una speranza, ce la togliete e ci uccidete.\""]},{"code":101,"indent":1,"parameters":["",0,0,2]},{"code":401,"indent":1,"parameters":["\\.\"Che effetto vi far\u00e0..."]},{"code":401,"indent":1,"parameters":["Riuscire a fare una cosa simile...?\""]},{"code":231,"indent":1,"parameters":[31,"cara15-7",1,0,408,312,100,100,255,0]},{"code":356,"indent":1,"parameters":["NameBoxSet Mina"]},{"code":101,"indent":1,"parameters":["",0,0,2]},{"code":401,"indent":1,"parameters":["\\.\"Beh...\""]},{"code":356,"indent":1,"parameters":["NameBoxSet Sara"]},{"code":101,"indent":1,"parameters":["",0,0,2]},{"code":401,"indent":1,"parameters":["\\.\"Le nostre vite... devono essere infime...\""]},{"code":101,"indent":1,"parameters":["",0,0,2]},{"code":401,"indent":1,"parameters":["\\.\"Quando moriamo, vi prendete anche"]},{"code":401,"indent":1,"parameters":["tutti i gettoni che guadagniamo? "]},{"code":231,"indent":1,"parameters":[31,"cara15-3",1,0,408,312,100,100,255,0]},{"code":356,"indent":1,"parameters":["NameBoxSet Mina"]},{"code":101,"indent":1,"parameters":["",0,0,2]},{"code":401,"indent":1,"parameters":["\\.\"Ehm...\""]},{"code":231,"indent":1,"parameters":[31,"cara15-1",1,0,408,312,100,100,255,0]},{"code":250,"indent":1,"parameters":[{"name":"Accent28-1","volume":90,"pitch":100,"pan":0}]},{"code":224,"indent":1,"parameters":[[255,255,255,170],60,false]},{"code":111,"indent":1,"parameters":[0,642,0]},{"code":231,"indent":2,"parameters":[31,"cara15-1",1,0,408,312,100,100,255,0]},{"code":356,"indent":2,"parameters":["NameBoxSet Mina"]},{"code":101,"indent":2,"parameters":["",0,0,2]},{"code":401,"indent":2,"parameters":["\\.\"Alice \\C[2]non aveva\\C[0] gettoni."]},{"code":0,"indent":2,"parameters":[]},{"code":411,"indent":1,"parameters":[]},{"code":231,"indent":2,"parameters":[31,"cara15-1",1,0,408,312,100,100,255,0]},{"code":356,"indent":2,"parameters":["NameBoxSet Mina"]},{"code":101,"indent":2,"parameters":["",0,0,2]},{"code":401,"indent":2,"parameters":["\\.\"Reko \\C[2]non aveva\\C[0] gettoni."]},{"code":0,"indent":2,"parameters":[]},{"code":412,"indent":1,"parameters":[]},{"code":0,"indent":1,"parameters":[]},{"code":402,"indent":0,"parameters":[1,"Inganna Mina"]},{"code":230,"indent":1,"parameters":[10]},{"code":122,"indent":1,"parameters":[288,288,0,0,1]},{"code":245,"indent":1,"parameters":[{"name":"","volume":90,"pitch":100,"pan":0}]},{"code":235,"indent":1,"parameters":[30]},{"code":250,"indent":1,"parameters":[{"name":"Accent28-1","volume":90,"pitch":100,"pan":0}]},{"code":224,"indent":1,"parameters":[[255,255,255,170],60,false]},{"code":356,"indent":1,"parameters":["NameBoxSet Sara"]},{"code":101,"indent":1,"parameters":["",0,0,2]},{"code":401,"indent":1,"parameters":["\"I miei gettoni sono qui da qualche parte...?\""]},{"code":231,"indent":1,"parameters":[31,"cara15-3",1,0,408,312,100,100,255,0]},{"code":356,"indent":1,"parameters":["NameBoxSet Mina"]},{"code":101,"indent":1,"parameters":["",0,0,2]},{"code":401,"indent":1,"parameters":["\\.\"Eh...?\""]},{"code":231,"indent":1,"parameters":[31,"cara15-1",1,0,408,312,100,100,255,0]},{"code":101,"indent":1,"parameters":["",0,0,2]},{"code":401,"indent":1,"parameters":["\\.\"Ha perso il suo portamonete?"]},{"code":401,"indent":1,"parameters":["Non l'ho visto da nessuna parte...\""]},{"code":250,"indent":1,"parameters":[{"name":"Accent21-1","volume":90,"pitch":100,"pan":0}]},{"code":224,"indent":1,"parameters":[[255,255,255,170],60,false]},{"code":356,"indent":1,"parameters":["NameBoxSet Sara"]},{"code":101,"indent":1,"parameters":["",0,0,2]},{"code":401,"indent":1,"parameters":["\\.\"Oh, non intendevo questo.\""]},{"code":231,"indent":1,"parameters":[30,"1an",1,0,408,312,2000,2000,0,0]},{"code":232,"indent":1,"parameters":[30,0,1,0,408,312,2000,2000,255,0,60,false]},{"code":250,"indent":1,"parameters":[{"name":"se_maoudamashii_magical14","volume":90,"pitch":100,"pan":0}]},{"code":224,"indent":1,"parameters":[[255,255,255,170],60,false]},{"code":111,"indent":1,"parameters":[0,642,0]},{"code":356,"indent":2,"parameters":["NameBoxSet Sara"]},{"code":101,"indent":2,"parameters":["",0,0,2]},{"code":401,"indent":2,"parameters":["\\.\"Ho affidato i miei gettoni ad Alice.\""]},{"code":0,"indent":2,"parameters":[]},{"code":411,"indent":1,"parameters":[]},{"code":356,"indent":2,"parameters":["NameBoxSet Sara"]},{"code":101,"indent":2,"parameters":["",0,0,2]},{"code":401,"indent":2,"parameters":["\\.\"Ho affidato i miei gettoni a Reko.\""]},{"code":0,"indent":2,"parameters":[]},{"code":412,"indent":1,"parameters":[]},{"code":101,"indent":1,"parameters":["",0,0,2]},{"code":401,"indent":1,"parameters":["\\.\"Tutti, temporaneamente, per un certo piano...\""]},{"code":231,"indent":1,"parameters":[31,"cara15-3",1,0,408,312,100,100,255,0]},{"code":356,"indent":1,"parameters":["NameBoxSet Mina"]},{"code":101,"indent":1,"parameters":["",0,0,2]},{"code":401,"indent":1,"parameters":["\\.\"..........\""]},{"code":356,"indent":1,"parameters":["NameBoxSet Sara"]},{"code":101,"indent":1,"parameters":["",0,0,2]},{"code":401,"indent":1,"parameters":["\\.\"Volevo riprendermeli, supponendo sopravvivesse...\""]},{"code":101,"indent":1,"parameters":["",0,0,2]},{"code":401,"indent":1,"parameters":["\\.\"E non abbiamo sentito nulla sul fatto"]},{"code":401,"indent":1,"parameters":["che i gettoni dei morti andassero perduti.\""]},{"code":101,"indent":1,"parameters":["",0,0,2]},{"code":401,"indent":1,"parameters":["\\.\"Quindi... potresti ridarmeli?\""]},{"code":231,"indent":1,"parameters":[31,"cara15-7",1,0,408,312,100,100,255,0]},{"code":356,"indent":1,"parameters":["NameBoxSet Mina"]},{"code":101,"indent":1,"parameters":["",0,0,2]},{"code":401,"indent":1,"parameters":["\\.\"Signorina Sara... ermm...\""]},{"code":232,"indent":1,"parameters":[30,0,1,0,408,312,2000,2000,0,0,30,false]},{"code":250,"indent":1,"parameters":[{"name":"Accent28-1","volume":90,"pitch":100,"pan":0}]},{"code":224,"indent":1,"parameters":[[255,255,255,170],60,false]},{"code":111,"indent":1,"parameters":[0,642,0]},{"code":231,"indent":2,"parameters":[31,"cara15-1",1,0,408,312,100,100,255,0]},{"code":356,"indent":2,"parameters":["NameBoxSet Mina"]},{"code":101,"indent":2,"parameters":["",0,0,2]},{"code":401,"indent":2,"parameters":["\\.\"Alice \\C[2]non aveva\\C[0] gettoni."]},{"code":0,"indent":2,"parameters":[]},{"code":411,"indent":1,"parameters":[]},{"code":231,"indent":2,"parameters":[31,"cara15-1",1,0,408,312,100,100,255,0]},{"code":356,"indent":2,"parameters":["NameBoxSet Mina"]},{"code":101,"indent":2,"parameters":["",0,0,2]},{"code":401,"indent":2,"parameters":["\\.\"Reko \\C[2]non aveva\\C[0] gettoni."]},{"code":0,"indent":2,"parameters":[]},{"code":412,"indent":1,"parameters":[]},{"code":0,"indent":1,"parameters":[]},{"code":404,"indent":0,"parameters":[]},{"code":356,"indent":0,"parameters":["NameBoxSet Sara"]},{"code":101,"indent":0,"parameters":["",0,0,2]},{"code":401,"indent":0,"parameters":["\\.\"Eh...?\""]},{"code":231,"indent":0,"parameters":[31,"cara15-2",1,0,408,312,100,100,255,0]},{"code":356,"indent":0,"parameters":["NameBoxSet Mina"]},{"code":101,"indent":0,"parameters":["",0,0,2]},{"code":401,"indent":0,"parameters":["\\.\"Scusi... Sono occupata, quindi con permesso...\""]},{"code":232,"indent":0,"parameters":[31,0,1,0,408,312,100,100,0,0,30,true]},{"code":235,"indent":0,"parameters":[31]},{"code":356,"indent":0,"parameters":["NameBoxSet Sara"]},{"code":101,"indent":0,"parameters":["",0,0,2]},{"code":401,"indent":0,"parameters":["\\.\\C[4](Che sta succedendo...?)"]},{"code":111,"indent":0,"parameters":[0,642,0]},{"code":356,"indent":1,"parameters":["NameBoxSet Sara"]},{"code":101,"indent":1,"parameters":["",0,0,2]},{"code":401,"indent":1,"parameters":["\\.\\C[4](Alice non aveva gettoni?)"]},{"code":250,"indent":1,"parameters":[{"name":"feed1","volume":90,"pitch":100,"pan":0}]},{"code":225,"indent":1,"parameters":[7,7,30,false]},{"code":101,"indent":1,"parameters":["",0,0,2]},{"code":401,"indent":1,"parameters":["\\.\\C[4](Impossibile...!"]},{"code":401,"indent":1,"parameters":["Alice era fra chi aveva pi\u00f9 gettoni!!)"]},{"code":0,"indent":1,"parameters":[]},{"code":411,"indent":0,"parameters":[]},{"code":356,"indent":1,"parameters":["NameBoxSet Sara"]},{"code":101,"indent":1,"parameters":["",0,0,2]},{"code":401,"indent":1,"parameters":["\\.\\C[4](Reko non aveva gettoni?)"]},{"code":250,"indent":1,"parameters":[{"name":"feed1","volume":90,"pitch":100,"pan":0}]},{"code":225,"indent":1,"parameters":[7,7,30,false]},{"code":101,"indent":1,"parameters":["",0,0,2]},{"code":401,"indent":1,"parameters":["\\.\\C[4](Impossibile...!"]},{"code":401,"indent":1,"parameters":["Reko doveva avere gettoni suoi, giusto?!)"]},{"code":0,"indent":1,"parameters":[]},{"code":412,"indent":0,"parameters":[]},{"code":231,"indent":0,"parameters":[30,"1an",1,0,408,312,2000,2000,0,0]},{"code":232,"indent":0,"parameters":[30,0,1,0,408,312,2000,2000,255,0,60,false]},{"code":356,"indent":0,"parameters":["NameBoxSet Sara"]},{"code":101,"indent":0,"parameters":["",0,0,2]},{"code":401,"indent":0,"parameters":["\\.\\C[4](Urgh... Qualcuno l'ha fatto per intrappolarmi...?)"]},{"code":101,"indent":0,"parameters":["",0,0,2]},{"code":401,"indent":0,"parameters":["\\.\"...\""]},{"code":250,"indent":0,"parameters":[{"name":"sceneswitch2","volume":90,"pitch":100,"pan":0}]},{"code":224,"indent":0,"parameters":[[255,255,255,170],60,false]},{"code":101,"indent":0,"parameters":["",0,0,2]},{"code":401,"indent":0,"parameters":["\\.\"Ahaha...\""]},{"code":111,"indent":0,"parameters":[1,288,0,1,0]},{"code":250,"indent":1,"parameters":[{"name":"Accent21-1","volume":90,"pitch":100,"pan":0}]},{"code":224,"indent":1,"parameters":[[255,255,255,170],60,false]},{"code":101,"indent":1,"parameters":["",0,0,2]},{"code":401,"indent":1,"parameters":["\\.\\C[4](Eh...? Perch\u00e9 rido?)"]},{"code":0,"indent":1,"parameters":[]},{"code":412,"indent":0,"parameters":[]},{"code":250,"indent":0,"parameters":[{"name":"feed1","volume":90,"pitch":100,"pan":0}]},{"code":224,"indent":0,"parameters":[[255,255,255,170],60,false]},{"code":101,"indent":0,"parameters":["",0,0,2]},{"code":401,"indent":0,"parameters":["\\.\"Ahahahahahahaha...!!\""]},{"code":245,"indent":0,"parameters":[{"name":"Darkness","volume":90,"pitch":100,"pan":0}]},{"code":231,"indent":0,"parameters":[31,"cara1-26",1,0,408,312,100,100,255,0]},{"code":232,"indent":0,"parameters":[31,0,1,0,408,312,100,100,255,0,30,false]},{"code":356,"indent":0,"parameters":["NameBoxSet Joe"]},{"code":101,"indent":0,"parameters":["",0,0,2]},{"code":401,"indent":0,"parameters":["\\.\\C[10]\"Ehil\u00e0. Ti diverti, Sara?\""]},{"code":356,"indent":0,"parameters":["NameBoxSet Sara"]},{"code":101,"indent":0,"parameters":["",0,0,2]},{"code":401,"indent":0,"parameters":["\\.\"S\u00ec... Non ho nemmeno pi\u00f9 le forze"]},{"code":401,"indent":0,"parameters":["per pensare a niente...\""]},{"code":250,"indent":0,"parameters":[{"name":"Accent28-1","volume":90,"pitch":70,"pan":0}]},{"code":224,"indent":0,"parameters":[[255,255,255,170],60,false]},{"code":356,"indent":0,"parameters":["NameBoxSet Joe"]},{"code":101,"indent":0,"parameters":["",0,0,2]},{"code":401,"indent":0,"parameters":["\\.\\C[10]\"Alla fine, suppongo che non stessi nemmeno"]},{"code":401,"indent":0,"parameters":["pensando seriamente a scappare, eh?\""]},{"code":250,"indent":0,"parameters":[{"name":"Accent21-1","volume":90,"pitch":70,"pan":0}]},{"code":224,"indent":0,"parameters":[[255,255,255,170],60,false]},{"code":356,"indent":0,"parameters":["NameBoxSet Sara"]},{"code":101,"indent":0,"parameters":["",0,0,2]},{"code":401,"indent":0,"parameters":["\\.\"Davvero...?\""]},{"code":356,"indent":0,"parameters":["NameBoxSet Joe"]},{"code":101,"indent":0,"parameters":["",0,0,2]},{"code":401,"indent":0,"parameters":["\\.\\C[10]\"Un mio presentimento. Trovi la speranza a"]},{"code":401,"indent":0,"parameters":["tutti gli altri... perch\u00e9 senza speranza muoiono."]},{"code":401,"indent":0,"parameters":["Era questo che pensavi?\""]},{"code":356,"indent":0,"parameters":["NameBoxSet Sara"]},{"code":101,"indent":0,"parameters":["",0,0,2]},{"code":401,"indent":0,"parameters":["\\.\"Ecco...\""]},{"code":102,"indent":0,"parameters":[["Hai ragione","Ti sbagli"],-1,-1,2,0]},{"code":402,"indent":0,"parameters":[0,"Hai ragione"]},{"code":230,"indent":1,"parameters":[10]},{"code":250,"indent":1,"parameters":[{"name":"Accent28-1","volume":90,"pitch":70,"pan":0}]},{"code":224,"indent":1,"parameters":[[255,255,255,170],60,false]},{"code":356,"indent":1,"parameters":["NameBoxSet Sara"]},{"code":101,"indent":1,"parameters":["",0,0,2]},{"code":401,"indent":1,"parameters":["\\.\"Gi\u00e0... mai pensavo di poterci morire.\""]},{"code":356,"indent":1,"parameters":["NameBoxSet Joe"]},{"code":101,"indent":1,"parameters":["",0,0,2]},{"code":401,"indent":1,"parameters":["\\.\\C[10]\"Alla fine te la tiri, eh?\""]},{"code":356,"indent":1,"parameters":["NameBoxSet Sara"]},{"code":101,"indent":1,"parameters":["",0,0,2]},{"code":401,"indent":1,"parameters":["\\.\"Ahahah... S\u00ec.\""]},{"code":101,"indent":1,"parameters":["",0,0,2]},{"code":401,"indent":1,"parameters":["\\.\"Onestamente, qualunque cosa faccia, sono incapace.\""]},{"code":0,"indent":1,"parameters":[]},{"code":402,"indent":0,"parameters":[1,"Ti sbagli"]},{"code":230,"indent":1,"parameters":[10]},{"code":250,"indent":1,"parameters":[{"name":"Accent28-1","volume":90,"pitch":70,"pan":0}]},{"code":224,"indent":1,"parameters":[[255,255,255,170],60,false]},{"code":356,"indent":1,"parameters":["NameBoxSet Sara"]},{"code":101,"indent":1,"parameters":["",0,0,2]},{"code":401,"indent":1,"parameters":["\\.\"Ti sbagli, Joe...\""]},{"code":101,"indent":1,"parameters":["",0,0,2]},{"code":401,"indent":1,"parameters":["\\.\"La speranza serviva a me.\""]},{"code":250,"indent":1,"parameters":[{"name":"Accent21-1","volume":90,"pitch":70,"pan":0}]},{"code":224,"indent":1,"parameters":[[255,255,255,170],60,false]},{"code":101,"indent":1,"parameters":["",0,0,2]},{"code":401,"indent":1,"parameters":["\\.\"Finch\u00e9 guardo avanti,"]},{"code":401,"indent":1,"parameters":["Posso ignorare la realt\u00e0 di averti ucciso.\""]},{"code":101,"indent":1,"parameters":["",0,0,2]},{"code":401,"indent":1,"parameters":["\\.\"Ma il futuro che mi attende al mio ritorno..."]},{"code":401,"indent":1,"parameters":["Posso solo immaginarlo nero come la pece.\""]},{"code":356,"indent":1,"parameters":["NameBoxSet Joe"]},{"code":101,"indent":1,"parameters":["",0,0,2]},{"code":401,"indent":1,"parameters":["\\.\\C[10]\"Che cacchio, Sara."]},{"code":401,"indent":1,"parameters":["Ci tenevi cos\u00ec tanto, a morire?\""]},{"code":250,"indent":1,"parameters":[{"name":"se_maoudamashii_magical14","volume":90,"pitch":70,"pan":0}]},{"code":224,"indent":1,"parameters":[[255,255,255,170],60,false]},{"code":356,"indent":1,"parameters":["NameBoxSet Sara"]},{"code":101,"indent":1,"parameters":["",0,0,2]},{"code":401,"indent":1,"parameters":["\\.\"Pu\u00f2 darsi... In fondo al cuore, io...\""]},{"code":101,"indent":1,"parameters":["",0,0,2]},{"code":401,"indent":1,"parameters":["\\.\"Ahahah...\""]},{"code":0,"indent":1,"parameters":[]},{"code":404,"indent":0,"parameters":[]},{"code":232,"indent":0,"parameters":[31,0,1,0,408,312,100,100,0,0,30,true]},{"code":235,"indent":0,"parameters":[31]},{"code":231,"indent":0,"parameters":[32,"sinohuti",0,0,0,0,100,100,0,0]},{"code":232,"indent":0,"parameters":[32,0,0,0,0,0,100,100,255,0,120,false]},{"code":246,"indent":0,"parameters":[2]},{"code":230,"indent":0,"parameters":[150]},{"code":231,"indent":0,"parameters":[29,"cara9-6",1,0,408,312,100,100,255,0]},{"code":356,"indent":0,"parameters":["NameBoxSet Sara"]},{"code":101,"indent":0,"parameters":["",0,0,2]},{"code":401,"indent":0,"parameters":["\\.\"Joe... Finalmente non devo pi\u00f9 sfuggirti.\""]},{"code":232,"indent":0,"parameters":[32,0,0,0,0,0,100,100,0,0,120,true]},{"code":235,"indent":0,"parameters":[32]},{"code":230,"indent":0,"parameters":[120]},{"code":250,"indent":0,"parameters":[{"name":"Thunder10","volume":90,"pitch":100,"pan":0}]},{"code":225,"indent":0,"parameters":[7,7,30,false]},{"code":231,"indent":0,"parameters":[100,"1siro",1,0,408,312,2000,2000,255,0]},{"code":230,"indent":0,"parameters":[1]},{"code":235,"indent":0,"parameters":[30]},{"code":232,"indent":0,"parameters":[100,0,1,0,408,312,2000,2000,0,0,60,false]},{"code":230,"indent":0,"parameters":[20]},{"code":356,"indent":0,"parameters":["NameBoxSet Gin"]},{"code":101,"indent":0,"parameters":["",0,0,2]},{"code":401,"indent":0,"parameters":["\"Sorellina Sara!! Resta con noi, miao!!\""]},{"code":250,"indent":0,"parameters":[{"name":"Accent28-1","volume":90,"pitch":100,"pan":0}]},{"code":224,"indent":0,"parameters":[[255,255,255,170],60,false]},{"code":356,"indent":0,"parameters":["NameBoxSet Sara"]},{"code":101,"indent":0,"parameters":["",0,0,2]},{"code":401,"indent":0,"parameters":["\\.\"Gin...?\""]},{"code":250,"indent":0,"parameters":[{"name":"feed1","volume":90,"pitch":100,"pan":0}]},{"code":225,"indent":0,"parameters":[7,7,30,false]},{"code":356,"indent":0,"parameters":["NameBoxSet Gin"]},{"code":101,"indent":0,"parameters":["",0,0,2]},{"code":401,"indent":0,"parameters":["\\.\"Il fratellino Joe non c'\u00e8, miao!!"]},{"code":401,"indent":0,"parameters":["Non dare retta a niente di strano, bau!!\""]},{"code":356,"indent":0,"parameters":["NameBoxSet Sara"]},{"code":101,"indent":0,"parameters":["",0,0,2]},{"code":401,"indent":0,"parameters":["\\.\"Perch\u00e9 sei qui, Gin...?\""]},{"code":231,"indent":0,"parameters":[31,"cara9-3",1,0,408,312,100,100,255,0]},{"code":235,"indent":0,"parameters":[29]},{"code":356,"indent":0,"parameters":["NameBoxSet Gin"]},{"code":101,"indent":0,"parameters":["",0,0,2]},{"code":401,"indent":0,"parameters":["\\.\"Perch\u00e9 sono qui...?\""]},{"code":231,"indent":0,"parameters":[31,"cara9-6",1,0,408,312,100,100,255,0]},{"code":250,"indent":0,"parameters":[{"name":"Damage4","volume":90,"pitch":100,"pan":0}]},{"code":224,"indent":0,"parameters":[[255,255,255,170],60,false]},{"code":225,"indent":0,"parameters":[7,7,30,false]},{"code":231,"indent":0,"parameters":[100,"1siro",1,0,408,312,2000,2000,0,0]},{"code":232,"indent":0,"parameters":[100,0,1,0,408,312,2000,2000,255,0,60,false]},{"code":101,"indent":0,"parameters":["",0,0,2]},{"code":401,"indent":0,"parameters":["\\.\"Ovviamente per tirare su la sorellina Sara!!!!\""]},{"code":231,"indent":0,"parameters":[50,"gin-ketui",0,0,0,0,100,100,255,0]},{"code":231,"indent":0,"parameters":[51,"gin-ketui1",1,0,394,289,100,100,255,0]},{"code":231,"indent":0,"parameters":[52,"gin-ketui2",1,0,394,289,100,100,0,0]},{"code":230,"indent":0,"parameters":[10]},{"code":232,"indent":0,"parameters":[100,0,1,0,408,312,2000,2000,0,0,60,true]},{"code":235,"indent":0,"parameters":[100]},{"code":235,"indent":0,"parameters":[31]},{"code":241,"indent":0,"parameters":[{"name":"ithukusimu","volume":75,"pitch":100,"pan":0}]},{"code":356,"indent":0,"parameters":["NameBoxSet Sara"]},{"code":101,"indent":0,"parameters":["",0,0,2]},{"code":401,"indent":0,"parameters":["\\.\"G-Gin?!\""]},{"code":356,"indent":0,"parameters":["NameBoxSet Gin"]},{"code":101,"indent":0,"parameters":["",0,0,2]},{"code":401,"indent":0,"parameters":["\\.\"Ti prego...! Torna in te!\""]},{"code":250,"indent":0,"parameters":[{"name":"feed1","volume":90,"pitch":100,"pan":0}]},{"code":225,"indent":0,"parameters":[7,7,30,false]},{"code":101,"indent":0,"parameters":["",0,0,2]},{"code":401,"indent":0,"parameters":["\\.\"Credi nel vero Joe!!"]},{"code":401,"indent":0,"parameters":["Ti prego, sorellina Sara...!!\""]},{"code":250,"indent":0,"parameters":[{"name":"Accent21-1","volume":90,"pitch":100,"pan":0}]},{"code":224,"indent":0,"parameters":[[255,255,255,170],60,false]},{"code":356,"indent":0,"parameters":["NameBoxSet Sara"]},{"code":101,"indent":0,"parameters":["",0,0,2]},{"code":401,"indent":0,"parameters":["\\.\"Credere... \\.\\.in Joe...?\""]},{"code":356,"indent":0,"parameters":["NameBoxSet Gin"]},{"code":101,"indent":0,"parameters":["",0,0,2]},{"code":401,"indent":0,"parameters":["\\.\"Non sei l'unica che non \u00e8"]},{"code":401,"indent":0,"parameters":["riuscita a fare niente, miao...!\""]},{"code":250,"indent":0,"parameters":[{"name":"feed1","volume":90,"pitch":100,"pan":0}]},{"code":225,"indent":0,"parameters":[7,7,30,false]},{"code":101,"indent":0,"parameters":["",0,0,2]},{"code":401,"indent":0,"parameters":["\\.\"Io... e tutti noi...!!\""]},{"code":101,"indent":0,"parameters":["",0,0,2]},{"code":401,"indent":0,"parameters":["\\.\"Abbiamo rimpianto, bau...!! Abbiamo sofferto, miao!!\""]},{"code":101,"indent":0,"parameters":["",0,0,2]},{"code":401,"indent":0,"parameters":["\\.\"Eppure... il fratellino Joe"]},{"code":401,"indent":0,"parameters":["alla fine sorrideva, miao...\""]},{"code":101,"indent":0,"parameters":["",0,0,2]},{"code":401,"indent":0,"parameters":["\\.\"E tutti gli altri che sono morti..."]},{"code":401,"indent":0,"parameters":["Pensavano a quelli che sarebbero rimasti"]},{"code":401,"indent":0,"parameters":["fino alla fine, bau!!\""]},{"code":250,"indent":0,"parameters":[{"name":"feed1","volume":90,"pitch":100,"pan":0}]},{"code":225,"indent":0,"parameters":[7,7,30,false]},{"code":101,"indent":0,"parameters":["",0,0,2]},{"code":401,"indent":0,"parameters":["\\.\"Quindi sono sicuro che voglia davvero"]},{"code":401,"indent":0,"parameters":["che tutti tornino a casa vivi!!\""]},{"code":101,"indent":0,"parameters":["",0,0,2]},{"code":401,"indent":0,"parameters":["\\.\"Ecco perch\u00e9...\""]},{"code":250,"indent":0,"parameters":[{"name":"Damage4","volume":90,"pitch":100,"pan":0}]},{"code":225,"indent":0,"parameters":[7,7,30,false]},{"code":101,"indent":0,"parameters":["",0,0,2]},{"code":401,"indent":0,"parameters":["\\.\"Devi credere nel vero Joe,"]},{"code":401,"indent":0,"parameters":["sorellina Sara...!!\""]},{"code":356,"indent":0,"parameters":["NameBoxSet Sara"]},{"code":101,"indent":0,"parameters":["",0,0,2]},{"code":401,"indent":0,"parameters":["\\.\"..........\""]},{"code":231,"indent":0,"parameters":[52,"gin-ketui2",1,0,394,289,100,100,0,0]},{"code":232,"indent":0,"parameters":[51,0,1,0,394,289,100,100,0,0,30,false]},{"code":232,"indent":0,"parameters":[52,0,1,0,394,289,100,100,255,0,30,false]},{"code":250,"indent":0,"parameters":[{"name":"Accent28-1","volume":90,"pitch":100,"pan":0}]},{"code":224,"indent":0,"parameters":[[255,255,255,170],60,false]},{"code":356,"indent":0,"parameters":["NameBoxSet Sara"]},{"code":101,"indent":0,"parameters":["",0,0,2]},{"code":401,"indent":0,"parameters":["\\.\"Il vero Joe...\""]},{"code":101,"indent":0,"parameters":["",0,0,2]},{"code":401,"indent":0,"parameters":["\\.\\C[4](Non lo so...)"]},{"code":101,"indent":0,"parameters":["",0,0,2]},{"code":401,"indent":0,"parameters":["\\.\\C[4](Sento... di averlo gi\u00e0 perso di vista...)"]},{"code":101,"indent":0,"parameters":["",0,0,2]},{"code":401,"indent":0,"parameters":["\\.\\C[4](Quel tipo che mi stava sempre accanto...)"]},{"code":242,"indent":0,"parameters":[2]},{"code":231,"indent":0,"parameters":[60,"1an",1,0,408,312,2000,2000,0,0]},{"code":232,"indent":0,"parameters":[60,0,1,0,408,312,2000,2000,255,0,60,true]},{"code":231,"indent":0,"parameters":[1,"1an",1,0,408,312,2000,2000,255,0]},{"code":235,"indent":0,"parameters":[15]},{"code":235,"indent":0,"parameters":[50]},{"code":235,"indent":0,"parameters":[51]},{"code":235,"indent":0,"parameters":[52]},{"code":231,"indent":0,"parameters":[61,"kouJoe2",1,0,408,292,100,100,0,0]},{"code":232,"indent":0,"parameters":[61,0,1,0,408,292,100,100,255,0,60,true]},{"code":356,"indent":0,"parameters":["NameBoxSet Sara"]},{"code":101,"indent":0,"parameters":["",0,0,2]},{"code":401,"indent":0,"parameters":["\\C[4](Ho il coraggio di affrontarlo a viso aperto...?)"]},{"code":356,"indent":0,"parameters":["P_CALL_CE 61 856 1 ON"]},{"code":232,"indent":0,"parameters":[60,0,1,0,408,312,2000,2000,0,0,30,true]},{"code":235,"indent":0,"parameters":[60]},{"code":121,"indent":0,"parameters":[989,989,0]},{"code":117,"indent":0,"parameters":[13]},{"code":0,"indent":0,"parameters":[]}],"moveFrequency":3,"moveRoute":{"list":[{"code":0,"parameters":[]}],"repeat":true,"skippable":false,"wait":false},"moveSpeed":3,"moveType":0,"priorityType":0,"stepAnime":false,"through":false,"trigger":3,"walkAnime":true},{"conditions":{"actorId":1,"actorValid":false,"itemId":1,"itemValid":false,"selfSwitchCh":"A","selfSwitchValid":false,"switch1Id":989,"switch1Valid":true,"switch2Id":1,"switch2Valid":false,"variableId":1,"variableValid":false,"variableValue":1020},"directionFix":false,"image":{"characterIndex":0,"characterName":"","direction":2,"pattern":0,"tileId":0},"list":[{"code":0,"indent":0,"parameters":[]}],"moveFrequency":3,"moveRoute":{"list":[{"code":0,"parameters":[]}],"repeat":true,"skippable":false,"wait":false},"moveSpeed":3,"moveType":0,"priorityType":0,"stepAnime":false,"through":false,"trigger":0,"walkAnime":true}],"x":0,"y":0},{"id":2,"name":"EV002","note":"","pages":[{"conditions":{"actorId":1,"actorValid":false,"itemId":1,"itemValid":false,"selfSwitchCh":"A","selfSwitchValid":false,"switch1Id":986,"switch1Valid":true,"switch2Id":1,"switch2Valid":false,"variableId":1,"variableValid":false,"variableValue":0},"directionFix":false,"image":{"characterIndex":0,"characterName":"","direction":2,"pattern":0,"tileId":0},"list":[{"code":111,"indent":0,"parameters":[1,320,0,5,1]},{"code":121,"indent":1,"parameters":[988,988,0]},{"code":0,"indent":1,"parameters":[]},{"code":411,"indent":0,"parameters":[]},{"code":111,"indent":1,"parameters":[1,279,0,180,1]},{"code":121,"indent":2,"parameters":[987,987,0]},{"code":0,"indent":2,"parameters":[]},{"code":412,"indent":1,"parameters":[]},{"code":0,"indent":1,"parameters":[]},{"code":412,"indent":0,"parameters":[]},{"code":230,"indent":0,"parameters":[1]},{"code":0,"indent":0,"parameters":[]}],"moveFrequency":3,"moveRoute":{"list":[{"code":0,"parameters":[]}],"repeat":true,"skippable":false,"wait":false},"moveSpeed":3,"moveType":0,"priorityType":0,"stepAnime":false,"through":false,"trigger":4,"walkAnime":true},{"conditions":{"actorId":1,"actorValid":false,"itemId":1,"itemValid":false,"selfSwitchCh":"A","selfSwitchValid":false,"switch1Id":988,"switch1Valid":true,"switch2Id":1,"switch2Valid":false,"variableId":1,"variableValid":false,"variableValue":0},"directionFix":false,"image":{"characterIndex":0,"characterName":"","direction":2,"pattern":0,"tileId":0},"list":[{"code":0,"indent":0,"parameters":[]}],"moveFrequency":3,"moveRoute":{"list":[{"code":0,"parameters":[]}],"repeat":true,"skippable":false,"wait":false},"moveSpeed":3,"moveType":0,"priorityType":0,"stepAnime":false,"through":false,"trigger":0,"walkAnime":true},{"conditions":{"actorId":1,"actorValid":false,"itemId":1,"itemValid":false,"selfSwitchCh":"A","selfSwitchValid":false,"switch1Id":987,"switch1Valid":true,"switch2Id":1,"switch2Valid":false,"variableId":1,"variableValid":false,"variableValue":0},"directionFix":false,"image":{"characterIndex":0,"characterName":"","direction":2,"pattern":0,"tileId":0},"list":[{"code":0,"indent":0,"parameters":[]}],"moveFrequency":3,"moveRoute":{"list":[{"code":0,"parameters":[]}],"repeat":true,"skippable":false,"wait":false},"moveSpeed":3,"moveType":0,"priorityType":0,"stepAnime":false,"through":false,"trigger":0,"walkAnime":true},{"conditions":{"actorId":1,"actorValid":false,"itemId":1,"itemValid":false,"selfSwitchCh":"A","selfSwitchValid":false,"switch1Id":1,"switch1Valid":false,"switch2Id":1,"switch2Valid":false,"variableId":1,"variableValid":true,"variableValue":1020},"directionFix":false,"image":{"characterIndex":0,"characterName":"","direction":2,"pattern":0,"tileId":0},"list":[{"code":0,"indent":0,"parameters":[]}],"moveFrequency":3,"moveRoute":{"list":[{"code":0,"parameters":[]}],"repeat":true,"skippable":false,"wait":false},"moveSpeed":3,"moveType":0,"priorityType":0,"stepAnime":false,"through":false,"trigger":0,"walkAnime":true}],"x":14,"y":2},{"id":3,"name":"EV003","note":"","pages":[{"conditions":{"actorId":1,"actorValid":false,"itemId":1,"itemValid":false,"selfSwitchCh":"A","selfSwitchValid":false,"switch1Id":986,"switch1Valid":true,"switch2Id":1,"switch2Valid":false,"variableId":1,"variableValid":false,"variableValue":0},"directionFix":false,"image":{"characterIndex":0,"characterName":"","direction":2,"pattern":0,"tileId":0},"list":[{"code":118,"indent":0,"parameters":["\u51fa\u623b\u308a\u756a\u9577"]},{"code":111,"indent":0,"parameters":[1,273,0,25,1]},{"code":111,"indent":1,"parameters":[0,961,0]},{"code":111,"indent":2,"parameters":[0,962,0]},{"code":111,"indent":3,"parameters":[0,963,0]},{"code":111,"indent":4,"parameters":[0,964,0]},{"code":122,"indent":5,"parameters":[273,273,0,0,0]},{"code":0,"indent":5,"parameters":[]},{"code":412,"indent":4,"parameters":[]},{"code":0,"indent":4,"parameters":[]},{"code":412,"indent":3,"parameters":[]},{"code":0,"indent":3,"parameters":[]},{"code":412,"indent":2,"parameters":[]},{"code":0,"indent":2,"parameters":[]},{"code":412,"indent":1,"parameters":[]},{"code":118,"indent":1,"parameters":["\u632f\u308a\u5206\u3051\u89aa\u65b9"]},{"code":122,"indent":1,"parameters":[271,271,0,2,1,4]},{"code":111,"indent":1,"parameters":[1,271,0,1,0]},{"code":111,"indent":2,"parameters":[0,961,1]},{"code":122,"indent":3,"parameters":[304,304,0,0,5]},{"code":122,"indent":3,"parameters":[316,316,0,0,1]},{"code":122,"indent":3,"parameters":[305,305,0,2,100,308]},{"code":122,"indent":3,"parameters":[306,306,0,2,100,262]},{"code":250,"indent":3,"parameters":[{"name":"Door2","volume":90,"pitch":100,"pan":0}]},{"code":231,"indent":3,"parameters":[62,"joete1",1,1,305,306,0,0,0,0]},{"code":232,"indent":3,"parameters":[62,0,1,1,305,306,40,40,255,0,30,false]},{"code":121,"indent":3,"parameters":[961,961,0]},{"code":122,"indent":3,"parameters":[273,273,0,0,0]},{"code":0,"indent":3,"parameters":[]},{"code":411,"indent":2,"parameters":[]},{"code":119,"indent":3,"parameters":["\u632f\u308a\u5206\u3051\u89aa\u65b9"]},{"code":0,"indent":3,"parameters":[]},{"code":412,"indent":2,"parameters":[]},{"code":0,"indent":2,"parameters":[]},{"code":411,"indent":1,"parameters":[]},{"code":111,"indent":2,"parameters":[1,271,0,2,0]},{"code":111,"indent":3,"parameters":[0,962,1]},{"code":122,"indent":4,"parameters":[307,307,0,0,5]},{"code":122,"indent":4,"parameters":[317,317,0,0,1]},{"code":122,"indent":4,"parameters":[308,308,0,2,100,308]},{"code":122,"indent":4,"parameters":[309,309,0,2,362,524]},{"code":250,"indent":4,"parameters":[{"name":"Door2","volume":90,"pitch":100,"pan":0}]},{"code":231,"indent":4,"parameters":[63,"joete1",1,1,308,309,0,0,0,0]},{"code":232,"indent":4,"parameters":[63,0,1,1,308,309,40,40,255,0,30,false]},{"code":121,"indent":4,"parameters":[962,962,0]},{"code":122,"indent":4,"parameters":[273,273,0,0,0]},{"code":0,"indent":4,"parameters":[]},{"code":411,"indent":3,"parameters":[]},{"code":119,"indent":4,"parameters":["\u632f\u308a\u5206\u3051\u89aa\u65b9"]},{"code":0,"indent":4,"parameters":[]},{"code":412,"indent":3,"parameters":[]},{"code":0,"indent":3,"parameters":[]},{"code":411,"indent":2,"parameters":[]},{"code":111,"indent":3,"parameters":[1,271,0,3,0]},{"code":111,"indent":4,"parameters":[0,963,1]},{"code":122,"indent":5,"parameters":[310,310,0,0,5]},{"code":122,"indent":5,"parameters":[318,318,0,0,1]},{"code":122,"indent":5,"parameters":[311,311,0,2,508,716]},{"code":122,"indent":5,"parameters":[312,312,0,2,100,262]},{"code":250,"indent":5,"parameters":[{"name":"Door2","volume":90,"pitch":100,"pan":0}]},{"code":231,"indent":5,"parameters":[64,"joete2",1,1,311,312,0,0,0,0]},{"code":232,"indent":5,"parameters":[64,0,1,1,311,312,40,40,255,0,30,false]},{"code":121,"indent":5,"parameters":[963,963,0]},{"code":122,"indent":5,"parameters":[273,273,0,0,0]},{"code":0,"indent":5,"parameters":[]},{"code":411,"indent":4,"parameters":[]},{"code":119,"indent":5,"parameters":["\u632f\u308a\u5206\u3051\u89aa\u65b9"]},{"code":0,"indent":5,"parameters":[]},{"code":412,"indent":4,"parameters":[]},{"code":0,"indent":4,"parameters":[]},{"code":411,"indent":3,"parameters":[]},{"code":111,"indent":4,"parameters":[1,271,0,4,0]},{"code":111,"indent":5,"parameters":[0,964,1]},{"code":122,"indent":6,"parameters":[313,313,0,0,5]},{"code":122,"indent":6,"parameters":[319,319,0,0,1]},{"code":122,"indent":6,"parameters":[314,314,0,2,508,716]},{"code":122,"indent":6,"parameters":[315,315,0,2,362,524]},{"code":250,"indent":6,"parameters":[{"name":"Door2","volume":90,"pitch":100,"pan":0}]},{"code":231,"indent":6,"parameters":[65,"joete2",1,1,314,315,0,0,0,0]},{"code":232,"indent":6,"parameters":[65,0,1,1,314,315,40,40,255,0,30,false]},{"code":121,"indent":6,"parameters":[964,964,0]},{"code":122,"indent":6,"parameters":[273,273,0,0,0]},{"code":0,"indent":6,"parameters":[]},{"code":411,"indent":5,"parameters":[]},{"code":119,"indent":6,"parameters":["\u632f\u308a\u5206\u3051\u89aa\u65b9"]},{"code":0,"indent":6,"parameters":[]},{"code":412,"indent":5,"parameters":[]},{"code":0,"indent":5,"parameters":[]},{"code":412,"indent":4,"parameters":[]},{"code":0,"indent":4,"parameters":[]},{"code":412,"indent":3,"parameters":[]},{"code":0,"indent":3,"parameters":[]},{"code":412,"indent":2,"parameters":[]},{"code":0,"indent":2,"parameters":[]},{"code":412,"indent":1,"parameters":[]},{"code":0,"indent":1,"parameters":[]},{"code":411,"indent":0,"parameters":[]},{"code":122,"indent":1,"parameters":[273,273,1,2,2,4]},{"code":230,"indent":1,"parameters":[10]},{"code":0,"indent":1,"parameters":[]},{"code":412,"indent":0,"parameters":[]},{"code":0,"indent":0,"parameters":[]}],"moveFrequency":3,"moveRoute":{"list":[{"code":0,"parameters":[]}],"repeat":true,"skippable":false,"wait":false},"moveSpeed":3,"moveType":0,"priorityType":0,"stepAnime":false,"through":false,"trigger":4,"walkAnime":true},{"conditions":{"actorId":1,"actorValid":false,"itemId":1,"itemValid":false,"selfSwitchCh":"A","selfSwitchValid":false,"switch1Id":988,"switch1Valid":true,"switch2Id":1,"switch2Valid":false,"variableId":1,"variableValid":false,"variableValue":0},"directionFix":false,"image":{"characterIndex":0,"characterName":"","direction":2,"pattern":0,"tileId":0},"list":[{"code":0,"indent":0,"parameters":[]}],"moveFrequency":3,"moveRoute":{"list":[{"code":0,"parameters":[]}],"repeat":true,"skippable":false,"wait":false},"moveSpeed":3,"moveType":0,"priorityType":0,"stepAnime":false,"through":false,"trigger":0,"walkAnime":true},{"conditions":{"actorId":1,"actorValid":false,"itemId":1,"itemValid":false,"selfSwitchCh":"A","selfSwitchValid":false,"switch1Id":987,"switch1Valid":true,"switch2Id":1,"switch2Valid":false,"variableId":1,"variableValid":false,"variableValue":0},"directionFix":false,"image":{"characterIndex":0,"characterName":"","direction":2,"pattern":0,"tileId":0},"list":[{"code":0,"indent":0,"parameters":[]}],"moveFrequency":3,"moveRoute":{"list":[{"code":0,"parameters":[]}],"repeat":true,"skippable":false,"wait":false},"moveSpeed":3,"moveType":0,"priorityType":0,"stepAnime":false,"through":false,"trigger":0,"walkAnime":true},{"conditions":{"actorId":1,"actorValid":false,"itemId":1,"itemValid":false,"selfSwitchCh":"A","selfSwitchValid":false,"switch1Id":1,"switch1Valid":false,"switch2Id":1,"switch2Valid":false,"variableId":1,"variableValid":true,"variableValue":1020},"directionFix":false,"image":{"characterIndex":0,"characterName":"","direction":2,"pattern":0,"tileId":0},"list":[{"code":0,"indent":0,"parameters":[]}],"moveFrequency":3,"moveRoute":{"list":[{"code":0,"parameters":[]}],"repeat":true,"skippable":false,"wait":false},"moveSpeed":3,"moveType":0,"priorityType":0,"stepAnime":false,"through":false,"trigger":0,"walkAnime":true}],"x":14,"y":1},{"id":4,"name":"EV004","note":"","pages":[{"conditions":{"actorId":1,"actorValid":false,"itemId":1,"itemValid":false,"selfSwitchCh":"A","selfSwitchValid":false,"switch1Id":986,"switch1Valid":true,"switch2Id":1,"switch2Valid":false,"variableId":1,"variableValid":false,"variableValue":0},"directionFix":false,"image":{"characterIndex":0,"characterName":"","direction":2,"pattern":0,"tileId":0},"list":[{"code":122,"indent":0,"parameters":[279,279,1,0,1]},{"code":230,"indent":0,"parameters":[10]},{"code":0,"indent":0,"parameters":[]}],"moveFrequency":3,"moveRoute":{"list":[{"code":0,"parameters":[]}],"repeat":true,"skippable":false,"wait":false},"moveSpeed":3,"moveType":0,"priorityType":0,"stepAnime":false,"through":false,"trigger":4,"walkAnime":true},{"conditions":{"actorId":1,"actorValid":false,"itemId":1,"itemValid":false,"selfSwitchCh":"A","selfSwitchValid":false,"switch1Id":988,"switch1Valid":true,"switch2Id":1,"switch2Valid":false,"variableId":1,"variableValid":false,"variableValue":0},"directionFix":false,"image":{"characterIndex":0,"characterName":"","direction":2,"pattern":0,"tileId":0},"list":[{"code":117,"indent":0,"parameters":[18]},{"code":241,"indent":0,"parameters":[{"name":"","volume":90,"pitch":100,"pan":0}]},{"code":250,"indent":0,"parameters":[{"name":"warning2","volume":90,"pitch":100,"pan":0}]},{"code":121,"indent":0,"parameters":[961,964,1]},{"code":224,"indent":0,"parameters":[[255,0,0,170],60,true]},{"code":231,"indent":0,"parameters":[90,"1an",1,0,408,312,2000,2000,0,0]},{"code":232,"indent":0,"parameters":[90,0,1,0,408,312,2000,2000,255,0,60,true]},{"code":250,"indent":0,"parameters":[{"name":"feed1","volume":90,"pitch":100,"pan":0}]},{"code":224,"indent":0,"parameters":[[255,0,0,170],60,false]},{"code":356,"indent":0,"parameters":["NameBoxSet Sara"]},{"code":101,"indent":0,"parameters":["",0,0,2]},{"code":401,"indent":0,"parameters":["\"U... Uaaaaah...!!!!\""]},{"code":245,"indent":0,"parameters":[{"name":"white_noise1","volume":70,"pitch":50,"pan":0}]},{"code":231,"indent":0,"parameters":[91,"joe-gennei",1,0,408,312,100,100,0,0]},{"code":232,"indent":0,"parameters":[91,0,1,0,408,330,110,110,255,0,300,false]},{"code":356,"indent":0,"parameters":["MSGSE TALK CLEAR"]},{"code":356,"indent":0,"parameters":["NameBoxReset "]},{"code":101,"indent":0,"parameters":["",0,2,2]},{"code":401,"indent":0,"parameters":["\\C[10]Non potrai mai dimenticarmi, Sara."]},{"code":356,"indent":0,"parameters":["MSGSE CONFIRM CLEAR"]},{"code":101,"indent":0,"parameters":["",0,2,2]},{"code":401,"indent":0,"parameters":["\\C[10]Sei gi\u00e0 distrutta."]},{"code":356,"indent":0,"parameters":["MSGSE TALK DEFAULT"]},{"code":356,"indent":0,"parameters":["MSGSE CONFIRM DEFAULT"]},{"code":245,"indent":0,"parameters":[{"name":"","volume":90,"pitch":100,"pan":0}]},{"code":224,"indent":0,"parameters":[[255,0,0,255],60,false]},{"code":235,"indent":0,"parameters":[91]},{"code":230,"indent":0,"parameters":[120]},{"code":250,"indent":0,"parameters":[{"name":"feed1","volume":90,"pitch":100,"pan":0}]},{"code":224,"indent":0,"parameters":[[255,255,255,170],60,false]},{"code":356,"indent":0,"parameters":["NameBoxSet Gin"]},{"code":101,"indent":0,"parameters":["",0,0,1]},{"code":401,"indent":0,"parameters":["\"Stai con noi! Sorellina Sara!!\""]},{"code":250,"indent":0,"parameters":[{"name":"Damage4","volume":90,"pitch":100,"pan":0}]},{"code":224,"indent":0,"parameters":[[255,255,255,170],60,false]},{"code":356,"indent":0,"parameters":["NameBoxSet Gin"]},{"code":101,"indent":0,"parameters":["",0,0,1]},{"code":401,"indent":0,"parameters":["\\.\"Sorellina Sara...!!\""]},{"code":230,"indent":0,"parameters":[90]},{"code":353,"indent":0,"parameters":[]},{"code":0,"indent":0,"parameters":[]}],"moveFrequency":3,"moveRoute":{"list":[{"code":0,"parameters":[]}],"repeat":true,"skippable":false,"wait":false},"moveSpeed":3,"moveType":0,"priorityType":0,"stepAnime":false,"through":false,"trigger":3,"walkAnime":true},{"conditions":{"actorId":1,"actorValid":false,"itemId":1,"itemValid":false,"selfSwitchCh":"A","selfSwitchValid":false,"switch1Id":987,"switch1Valid":true,"switch2Id":1,"switch2Valid":false,"variableId":1,"variableValid":false,"variableValue":0},"directionFix":false,"image":{"characterIndex":0,"characterName":"","direction":2,"pattern":0,"tileId":0},"list":[{"code":117,"indent":0,"parameters":[18]},{"code":242,"indent":0,"parameters":[2]},{"code":121,"indent":0,"parameters":[961,964,1]},{"code":250,"indent":0,"parameters":[{"name":"se_maoudamashii_magical14","volume":90,"pitch":100,"pan":0}]},{"code":224,"indent":0,"parameters":[[255,255,255,170],60,true]},{"code":224,"indent":0,"parameters":[[255,255,255,170],60,true]},{"code":224,"indent":0,"parameters":[[255,255,255,170],60,true]},{"code":230,"indent":0,"parameters":[30]},{"code":231,"indent":0,"parameters":[70,"1an",1,0,408,312,2000,2000,0,0]},{"code":232,"indent":0,"parameters":[70,0,1,0,408,312,2000,2000,255,0,30,true]},{"code":235,"indent":0,"parameters":[1]},{"code":235,"indent":0,"parameters":[61]},{"code":235,"indent":0,"parameters":[62]},{"code":235,"indent":0,"parameters":[63]},{"code":235,"indent":0,"parameters":[64]},{"code":235,"indent":0,"parameters":[65]},{"code":231,"indent":0,"parameters":[72,"cara1-27",1,0,408,312,100,100,0,0]},{"code":231,"indent":0,"parameters":[75,"cara1-26",1,0,408,312,100,100,0,0]},{"code":232,"indent":0,"parameters":[75,0,1,0,408,312,100,100,255,0,30,true]},{"code":231,"indent":0,"parameters":[74,"cara1-27",1,0,408,312,100,100,255,0]},{"code":356,"indent":0,"parameters":["NameBoxSet Joe?"]},{"code":101,"indent":0,"parameters":["",0,0,2]},{"code":401,"indent":0,"parameters":["\\C[10]\"Tch...\""]},{"code":232,"indent":0,"parameters":[75,0,1,0,408,312,100,100,0,0,30,true]},{"code":235,"indent":0,"parameters":[75]},{"code":231,"indent":0,"parameters":[73,"cara1-28",1,0,408,312,100,100,255,0]},{"code":101,"indent":0,"parameters":["",0,0,2]},{"code":401,"indent":0,"parameters":["\\.\\C[10]\"Sei gi\u00e0 distrutta.\""]},{"code":232,"indent":0,"parameters":[74,0,1,0,408,312,100,100,0,0,30,true]},{"code":235,"indent":0,"parameters":[74]},{"code":231,"indent":0,"parameters":[72,"cara1-29",1,0,408,312,100,100,255,0]},{"code":101,"indent":0,"parameters":["",0,0,2]},{"code":401,"indent":0,"parameters":["\\.\\C[10]\"E' impossibile eliminarmi per sempre.\""]},{"code":232,"indent":0,"parameters":[73,0,1,0,408,312,100,100,0,0,30,true]},{"code":235,"indent":0,"parameters":[73]},{"code":231,"indent":0,"parameters":[71,"cara1-30",1,0,408,312,100,100,255,0]},{"code":101,"indent":0,"parameters":["",0,0,2]},{"code":401,"indent":0,"parameters":["\\.\\C[10]\"...See ya later.\""]},{"code":232,"indent":0,"parameters":[72,0,1,0,408,312,100,100,0,0,30,true]},{"code":235,"indent":0,"parameters":[72]},{"code":232,"indent":0,"parameters":[71,0,1,0,408,312,100,100,0,0,30,true]},{"code":235,"indent":0,"parameters":[71]},{"code":231,"indent":0,"parameters":[31,"cara9-3",1,0,408,312,100,100,255,0]},{"code":230,"indent":0,"parameters":[60]},{"code":232,"indent":0,"parameters":[70,0,1,0,408,312,2000,2000,0,0,60,true]},{"code":235,"indent":0,"parameters":[70]},{"code":231,"indent":0,"parameters":[31,"cara9-10",1,0,408,312,100,100,255,0]},{"code":250,"indent":0,"parameters":[{"name":"Accent21-1","volume":90,"pitch":100,"pan":0}]},{"code":224,"indent":0,"parameters":[[255,255,255,170],60,false]},{"code":356,"indent":0,"parameters":["NameBoxSet Gin"]},{"code":101,"indent":0,"parameters":["",0,0,2]},{"code":401,"indent":0,"parameters":["\"Sorellina Sara...?\""]},{"code":356,"indent":0,"parameters":["NameBoxSet Sara"]},{"code":101,"indent":0,"parameters":["",0,0,2]},{"code":401,"indent":0,"parameters":["\\.\"Gin...\""]},{"code":250,"indent":0,"parameters":[{"name":"Accent28-1","volume":90,"pitch":100,"pan":0}]},{"code":224,"indent":0,"parameters":[[255,255,255,170],60,false]},{"code":101,"indent":0,"parameters":["",0,0,2]},{"code":401,"indent":0,"parameters":["\\.\"Grazie...\""]},{"code":241,"indent":0,"parameters":[{"name":"samuraionnna","volume":80,"pitch":100,"pan":0}]},{"code":101,"indent":0,"parameters":["",0,0,2]},{"code":401,"indent":0,"parameters":["\\.\"Io... Avevo scordato qualcosa di importante.\""]},{"code":231,"indent":0,"parameters":[31,"cara9-1",1,0,408,312,100,100,255,0]},{"code":356,"indent":0,"parameters":["NameBoxSet Gin"]},{"code":101,"indent":0,"parameters":["",0,0,2]},{"code":401,"indent":0,"parameters":["\\.\"Sei... tornata normale, bau?\""]},{"code":250,"indent":0,"parameters":[{"name":"se_maoudamashii_magical14","volume":90,"pitch":100,"pan":0}]},{"code":224,"indent":0,"parameters":[[255,255,255,170],60,false]},{"code":356,"indent":0,"parameters":["NameBoxSet Sara"]},{"code":101,"indent":0,"parameters":["",0,0,2]},{"code":401,"indent":0,"parameters":["\\.\"S\u00ec. Torniamo tutti vivi... insieme.\""]},{"code":101,"indent":0,"parameters":["",0,0,2]},{"code":401,"indent":0,"parameters":["\\.\"Non lascer\u00f2 che nessun altro perda la vita.\""]},{"code":231,"indent":0,"parameters":[31,"cara0-3",1,0,408,312,100,100,255,0]},{"code":250,"indent":0,"parameters":[{"name":"Thunder10","volume":90,"pitch":100,"pan":0}]},{"code":224,"indent":0,"parameters":[[255,255,255,170],60,false]},{"code":101,"indent":0,"parameters":["",0,0,2]},{"code":401,"indent":0,"parameters":["\\.\"Non lascer\u00f2 che i rapitori l'abbiano vinta!\""]},{"code":231,"indent":0,"parameters":[31,"cara9-11",1,0,408,312,100,100,255,0]},{"code":250,"indent":0,"parameters":[{"name":"flash-of-light-3","volume":90,"pitch":100,"pan":0}]},{"code":224,"indent":0,"parameters":[[255,255,255,170],60,false]},{"code":356,"indent":0,"parameters":["NameBoxSet Gin"]},{"code":101,"indent":0,"parameters":["",0,0,2]},{"code":401,"indent":0,"parameters":["\\.\"S\u00ec!\""]},{"code":231,"indent":0,"parameters":[30,"1siro",1,0,408,312,2000,2000,0,0]},{"code":232,"indent":0,"parameters":[30,0,1,0,408,312,2000,2000,255,0,60,false]},{"code":356,"indent":0,"parameters":["NameBoxSet Sara"]},{"code":101,"indent":0,"parameters":["",0,0,2]},{"code":401,"indent":0,"parameters":["\\.\\C[4](Scoppio di energia...)"]},{"code":101,"indent":0,"parameters":["",0,0,2]},{"code":401,"indent":0,"parameters":["\\.\\C[4](C'\u00e8 pi\u00f9 della mia vita e basta...!)"]},{"code":101,"indent":0,"parameters":["",0,0,2]},{"code":401,"indent":0,"parameters":["\\.\\C[4](Per proteggere tutti... andr\u00f2 avanti!)"]},{"code":242,"indent":0,"parameters":[1]},{"code":232,"indent":0,"parameters":[30,0,1,0,408,312,2000,2000,0,0,60,true]},{"code":231,"indent":0,"parameters":[31,"cara9-6",1,0,408,312,100,100,255,0]},{"code":250,"indent":0,"parameters":[{"name":"Accent21-1","volume":90,"pitch":100,"pan":0}]},{"code":224,"indent":0,"parameters":[[255,255,255,170],60,false]},{"code":356,"indent":0,"parameters":["NameBoxSet Gin"]},{"code":101,"indent":0,"parameters":["",0,0,2]},{"code":401,"indent":0,"parameters":["\\.\"Sorellina Sara! Andiamo, bau!\""]},{"code":241,"indent":0,"parameters":[{"name":"tansaku3","volume":100,"pitch":100,"pan":0}]},{"code":232,"indent":0,"parameters":[31,0,1,0,408,312,100,100,0,0,30,true]},{"code":231,"indent":0,"parameters":[16,"aibou9-1",1,0,680,528,100,100,0,0]},{"code":232,"indent":0,"parameters":[16,0,1,0,680,528,100,100,255,0,60,true]},{"code":356,"indent":0,"parameters":["P_CALL_CE 16 966 1 ON"]},{"code":117,"indent":0,"parameters":[13]},{"code":117,"indent":0,"parameters":[21]},{"code":126,"indent":0,"parameters":[116,0,0,1]},{"code":122,"indent":0,"parameters":[1,1,0,0,1020]},{"code":231,"indent":0,"parameters":[14,"menu",1,0,106,572,100,100,0,0]},{"code":231,"indent":0,"parameters":[15,"idou",1,0,298,572,100,100,0,0]},{"code":232,"indent":0,"parameters":[14,0,1,0,106,572,100,100,255,0,30,false]},{"code":232,"indent":0,"parameters":[15,0,1,0,298,572,100,100,255,0,30,true]},{"code":117,"indent":0,"parameters":[13]},{"code":0,"indent":0,"parameters":[]}],"moveFrequency":3,"moveRoute":{"list":[{"code":0,"parameters":[]}],"repeat":true,"skippable":false,"wait":false},"moveSpeed":3,"moveType":0,"priorityType":0,"stepAnime":false,"through":false,"trigger":3,"walkAnime":true},{"conditions":{"actorId":1,"actorValid":false,"itemId":1,"itemValid":false,"selfSwitchCh":"A","selfSwitchValid":false,"switch1Id":1,"switch1Valid":false,"switch2Id":1,"switch2Valid":false,"variableId":1,"variableValid":true,"variableValue":1020},"directionFix":false,"image":{"characterIndex":0,"characterName":"","direction":2,"pattern":0,"tileId":0},"list":[{"code":0,"indent":0,"parameters":[]}],"moveFrequency":3,"moveRoute":{"list":[{"code":0,"parameters":[]}],"repeat":true,"skippable":false,"wait":false},"moveSpeed":3,"moveType":0,"priorityType":0,"stepAnime":false,"through":false,"trigger":0,"walkAnime":true}],"x":14,"y":0},{"id":5,"name":"EV005","note":"","pages":[{"conditions":{"actorId":1,"actorValid":false,"itemId":1,"itemValid":false,"selfSwitchCh":"A","selfSwitchValid":false,"switch1Id":986,"switch1Valid":true,"switch2Id":961,"switch2Valid":true,"variableId":1,"variableValid":false,"variableValue":0},"directionFix":false,"image":{"characterIndex":0,"characterName":"","direction":2,"pattern":0,"tileId":0},"list":[{"code":122,"indent":0,"parameters":[304,304,1,0,1]},{"code":230,"indent":0,"parameters":[10]},{"code":111,"indent":0,"parameters":[1,316,0,5,0]},{"code":111,"indent":1,"parameters":[1,304,0,30,2]},{"code":121,"indent":2,"parameters":[961,961,1]},{"code":122,"indent":2,"parameters":[304,304,0,0,0]},{"code":122,"indent":2,"parameters":[316,316,0,0,0]},{"code":250,"indent":2,"parameters":[{"name":"Damage3","volume":90,"pitch":100,"pan":0}]},{"code":224,"indent":2,"parameters":[[255,0,0,170],60,false]},{"code":235,"indent":2,"parameters":[62]},{"code":122,"indent":2,"parameters":[320,320,1,0,1]},{"code":0,"indent":2,"parameters":[]},{"code":412,"indent":1,"parameters":[]},{"code":0,"indent":1,"parameters":[]},{"code":411,"indent":0,"parameters":[]},{"code":111,"indent":1,"parameters":[1,316,0,4,0]},{"code":111,"indent":2,"parameters":[1,304,0,25,2]},{"code":122,"indent":3,"parameters":[304,304,0,0,25]},{"code":122,"indent":3,"parameters":[316,316,0,0,5]},{"code":232,"indent":3,"parameters":[62,0,1,1,305,306,100,100,255,0,10,false]},{"code":0,"indent":3,"parameters":[]},{"code":412,"indent":2,"parameters":[]},{"code":0,"indent":2,"parameters":[]},{"code":411,"indent":1,"parameters":[]},{"code":111,"indent":2,"parameters":[1,316,0,3,0]},{"code":111,"indent":3,"parameters":[1,304,0,20,1]},{"code":122,"indent":4,"parameters":[304,304,0,0,20]},{"code":122,"indent":4,"parameters":[316,316,0,0,4]},{"code":232,"indent":4,"parameters":[62,0,1,1,305,306,80,80,255,0,10,false]},{"code":0,"indent":4,"parameters":[]},{"code":412,"indent":3,"parameters":[]},{"code":0,"indent":3,"parameters":[]},{"code":411,"indent":2,"parameters":[]},{"code":111,"indent":3,"parameters":[1,316,0,2,0]},{"code":111,"indent":4,"parameters":[1,304,0,15,1]},{"code":122,"indent":5,"parameters":[304,304,0,0,15]},{"code":122,"indent":5,"parameters":[316,316,0,0,3]},{"code":232,"indent":5,"parameters":[62,0,1,1,305,306,65,65,255,0,10,false]},{"code":0,"indent":5,"parameters":[]},{"code":412,"indent":4,"parameters":[]},{"code":0,"indent":4,"parameters":[]},{"code":411,"indent":3,"parameters":[]},{"code":111,"indent":4,"parameters":[1,316,0,1,0]},{"code":111,"indent":5,"parameters":[1,304,0,10,1]},{"code":122,"indent":6,"parameters":[304,304,0,0,10]},{"code":122,"indent":6,"parameters":[316,316,0,0,2]},{"code":232,"indent":6,"parameters":[62,0,1,1,305,306,50,50,255,0,10,false]},{"code":0,"indent":6,"parameters":[]},{"code":412,"indent":5,"parameters":[]},{"code":0,"indent":5,"parameters":[]},{"code":411,"indent":4,"parameters":[]},{"code":111,"indent":5,"parameters":[1,316,0,0,0]},{"code":111,"indent":6,"parameters":[1,304,0,5,1]},{"code":122,"indent":7,"parameters":[304,304,0,0,5]},{"code":122,"indent":7,"parameters":[316,316,0,0,1]},{"code":232,"indent":7,"parameters":[62,0,1,1,305,306,40,40,255,0,10,false]},{"code":0,"indent":7,"parameters":[]},{"code":412,"indent":6,"parameters":[]},{"code":0,"indent":6,"parameters":[]},{"code":412,"indent":5,"parameters":[]},{"code":0,"indent":5,"parameters":[]},{"code":412,"indent":4,"parameters":[]},{"code":0,"indent":4,"parameters":[]},{"code":412,"indent":3,"parameters":[]},{"code":0,"indent":3,"parameters":[]},{"code":412,"indent":2,"parameters":[]},{"code":0,"indent":2,"parameters":[]},{"code":412,"indent":1,"parameters":[]},{"code":0,"indent":1,"parameters":[]},{"code":412,"indent":0,"parameters":[]},{"code":0,"indent":0,"parameters":[]}],"moveFrequency":3,"moveRoute":{"list":[{"code":0,"parameters":[]}],"repeat":true,"skippable":false,"wait":false},"moveSpeed":3,"moveType":0,"priorityType":0,"stepAnime":false,"through":false,"trigger":4,"walkAnime":true},{"conditions":{"actorId":1,"actorValid":false,"itemId":1,"itemValid":false,"selfSwitchCh":"A","selfSwitchValid":false,"switch1Id":987,"switch1Valid":true,"switch2Id":1,"switch2Valid":false,"variableId":1,"variableValid":false,"variableValue":0},"directionFix":false,"image":{"characterIndex":0,"characterName":"","direction":2,"pattern":0,"tileId":0},"list":[{"code":0,"indent":0,"parameters":[]}],"moveFrequency":3,"moveRoute":{"list":[{"code":0,"parameters":[]}],"repeat":true,"skippable":false,"wait":false},"moveSpeed":3,"moveType":0,"priorityType":0,"stepAnime":false,"through":false,"trigger":0,"walkAnime":true},{"conditions":{"actorId":1,"actorValid":false,"itemId":1,"itemValid":false,"selfSwitchCh":"A","selfSwitchValid":false,"switch1Id":988,"switch1Valid":true,"switch2Id":1,"switch2Valid":false,"variableId":1,"variableValid":false,"variableValue":0},"directionFix":false,"image":{"characterIndex":0,"characterName":"","direction":2,"pattern":0,"tileId":0},"list":[{"code":0,"indent":0,"parameters":[]}],"moveFrequency":3,"moveRoute":{"list":[{"code":0,"parameters":[]}],"repeat":true,"skippable":false,"wait":false},"moveSpeed":3,"moveType":0,"priorityType":0,"stepAnime":false,"through":false,"trigger":0,"walkAnime":true}],"x":12,"y":0},{"id":6,"name":"EV006","note":"","pages":[{"conditions":{"actorId":1,"actorValid":false,"itemId":1,"itemValid":false,"selfSwitchCh":"A","selfSwitchValid":false,"switch1Id":986,"switch1Valid":true,"switch2Id":962,"switch2Valid":true,"variableId":1,"variableValid":false,"variableValue":0},"directionFix":false,"image":{"characterIndex":0,"characterName":"","direction":2,"pattern":0,"tileId":0},"list":[{"code":122,"indent":0,"parameters":[307,307,1,0,1]},{"code":230,"indent":0,"parameters":[10]},{"code":111,"indent":0,"parameters":[1,317,0,5,0]},{"code":111,"indent":1,"parameters":[1,307,0,30,1]},{"code":121,"indent":2,"parameters":[962,962,1]},{"code":122,"indent":2,"parameters":[307,307,0,0,0]},{"code":122,"indent":2,"parameters":[317,317,0,0,0]},{"code":250,"indent":2,"parameters":[{"name":"Damage3","volume":90,"pitch":100,"pan":0}]},{"code":224,"indent":2,"parameters":[[255,0,0,170],60,false]},{"code":235,"indent":2,"parameters":[63]},{"code":122,"indent":2,"parameters":[320,320,1,0,1]},{"code":0,"indent":2,"parameters":[]},{"code":412,"indent":1,"parameters":[]},{"code":0,"indent":1,"parameters":[]},{"code":411,"indent":0,"parameters":[]},{"code":111,"indent":1,"parameters":[1,317,0,4,0]},{"code":111,"indent":2,"parameters":[1,307,0,25,1]},{"code":122,"indent":3,"parameters":[307,307,0,0,25]},{"code":122,"indent":3,"parameters":[317,317,0,0,5]},{"code":232,"indent":3,"parameters":[63,0,1,1,308,309,100,100,255,0,10,false]},{"code":0,"indent":3,"parameters":[]},{"code":412,"indent":2,"parameters":[]},{"code":0,"indent":2,"parameters":[]},{"code":411,"indent":1,"parameters":[]},{"code":111,"indent":2,"parameters":[1,317,0,3,0]},{"code":111,"indent":3,"parameters":[1,307,0,20,1]},{"code":122,"indent":4,"parameters":[307,307,0,0,20]},{"code":122,"indent":4,"parameters":[317,317,0,0,4]},{"code":232,"indent":4,"parameters":[63,0,1,1,308,309,80,80,255,0,10,false]},{"code":0,"indent":4,"parameters":[]},{"code":412,"indent":3,"parameters":[]},{"code":0,"indent":3,"parameters":[]},{"code":411,"indent":2,"parameters":[]},{"code":111,"indent":3,"parameters":[1,317,0,2,0]},{"code":111,"indent":4,"parameters":[1,307,0,15,1]},{"code":122,"indent":5,"parameters":[307,307,0,0,15]},{"code":122,"indent":5,"parameters":[317,317,0,0,3]},{"code":232,"indent":5,"parameters":[63,0,1,1,308,309,65,65,255,0,10,false]},{"code":0,"indent":5,"parameters":[]},{"code":412,"indent":4,"parameters":[]},{"code":0,"indent":4,"parameters":[]},{"code":411,"indent":3,"parameters":[]},{"code":111,"indent":4,"parameters":[1,317,0,1,0]},{"code":111,"indent":5,"parameters":[1,307,0,10,1]},{"code":122,"indent":6,"parameters":[307,307,0,0,10]},{"code":122,"indent":6,"parameters":[317,317,0,0,2]},{"code":232,"indent":6,"parameters":[63,0,1,1,308,309,50,50,255,0,10,false]},{"code":0,"indent":6,"parameters":[]},{"code":412,"indent":5,"parameters":[]},{"code":0,"indent":5,"parameters":[]},{"code":411,"indent":4,"parameters":[]},{"code":111,"indent":5,"parameters":[1,317,0,0,0]},{"code":111,"indent":6,"parameters":[1,307,0,5,1]},{"code":122,"indent":7,"parameters":[307,307,0,0,5]},{"code":122,"indent":7,"parameters":[317,317,0,0,1]},{"code":232,"indent":7,"parameters":[63,0,1,1,308,309,40,40,255,0,10,false]},{"code":0,"indent":7,"parameters":[]},{"code":412,"indent":6,"parameters":[]},{"code":0,"indent":6,"parameters":[]},{"code":412,"indent":5,"parameters":[]},{"code":0,"indent":5,"parameters":[]},{"code":412,"indent":4,"parameters":[]},{"code":0,"indent":4,"parameters":[]},{"code":412,"indent":3,"parameters":[]},{"code":0,"indent":3,"parameters":[]},{"code":412,"indent":2,"parameters":[]},{"code":0,"indent":2,"parameters":[]},{"code":412,"indent":1,"parameters":[]},{"code":0,"indent":1,"parameters":[]},{"code":412,"indent":0,"parameters":[]},{"code":0,"indent":0,"parameters":[]}],"moveFrequency":3,"moveRoute":{"list":[{"code":0,"parameters":[]}],"repeat":true,"skippable":false,"wait":false},"moveSpeed":3,"moveType":0,"priorityType":0,"stepAnime":false,"through":false,"trigger":4,"walkAnime":true},{"conditions":{"actorId":1,"actorValid":false,"itemId":1,"itemValid":false,"selfSwitchCh":"A","selfSwitchValid":false,"switch1Id":987,"switch1Valid":true,"switch2Id":1,"switch2Valid":false,"variableId":1,"variableValid":false,"variableValue":0},"directionFix":false,"image":{"characterIndex":0,"characterName":"","direction":2,"pattern":0,"tileId":0},"list":[{"code":0,"indent":0,"parameters":[]}],"moveFrequency":3,"moveRoute":{"list":[{"code":0,"parameters":[]}],"repeat":true,"skippable":false,"wait":false},"moveSpeed":3,"moveType":0,"priorityType":0,"stepAnime":false,"through":false,"trigger":0,"walkAnime":true},{"conditions":{"actorId":1,"actorValid":false,"itemId":1,"itemValid":false,"selfSwitchCh":"A","selfSwitchValid":false,"switch1Id":988,"switch1Valid":true,"switch2Id":1,"switch2Valid":false,"variableId":1,"variableValid":false,"variableValue":0},"directionFix":false,"image":{"characterIndex":0,"characterName":"","direction":2,"pattern":0,"tileId":0},"list":[{"code":0,"indent":0,"parameters":[]}],"moveFrequency":3,"moveRoute":{"list":[{"code":0,"parameters":[]}],"repeat":true,"skippable":false,"wait":false},"moveSpeed":3,"moveType":0,"priorityType":0,"stepAnime":false,"through":false,"trigger":0,"walkAnime":true}],"x":12,"y":1},{"id":7,"name":"EV007","note":"","pages":[{"conditions":{"actorId":1,"actorValid":false,"itemId":1,"itemValid":false,"selfSwitchCh":"A","selfSwitchValid":false,"switch1Id":986,"switch1Valid":true,"switch2Id":963,"switch2Valid":true,"variableId":1,"variableValid":false,"variableValue":0},"directionFix":false,"image":{"characterIndex":0,"characterName":"","direction":2,"pattern":0,"tileId":0},"list":[{"code":122,"indent":0,"parameters":[310,310,1,0,1]},{"code":230,"indent":0,"parameters":[10]},{"code":111,"indent":0,"parameters":[1,318,0,5,0]},{"code":111,"indent":1,"parameters":[1,310,0,30,1]},{"code":121,"indent":2,"parameters":[963,963,1]},{"code":122,"indent":2,"parameters":[310,310,0,0,0]},{"code":122,"indent":2,"parameters":[318,318,0,0,0]},{"code":250,"indent":2,"parameters":[{"name":"Damage3","volume":90,"pitch":100,"pan":0}]},{"code":224,"indent":2,"parameters":[[255,0,0,170],60,false]},{"code":235,"indent":2,"parameters":[64]},{"code":122,"indent":2,"parameters":[320,320,1,0,1]},{"code":0,"indent":2,"parameters":[]},{"code":412,"indent":1,"parameters":[]},{"code":0,"indent":1,"parameters":[]},{"code":411,"indent":0,"parameters":[]},{"code":111,"indent":1,"parameters":[1,318,0,4,0]},{"code":111,"indent":2,"parameters":[1,310,0,25,1]},{"code":122,"indent":3,"parameters":[310,310,0,0,25]},{"code":122,"indent":3,"parameters":[318,318,0,0,5]},{"code":232,"indent":3,"parameters":[64,0,1,1,311,312,100,100,255,0,10,false]},{"code":0,"indent":3,"parameters":[]},{"code":412,"indent":2,"parameters":[]},{"code":0,"indent":2,"parameters":[]},{"code":411,"indent":1,"parameters":[]},{"code":111,"indent":2,"parameters":[1,318,0,3,0]},{"code":111,"indent":3,"parameters":[1,310,0,20,1]},{"code":122,"indent":4,"parameters":[310,310,0,0,20]},{"code":122,"indent":4,"parameters":[318,318,0,0,4]},{"code":232,"indent":4,"parameters":[64,0,1,1,311,312,80,80,255,0,10,false]},{"code":0,"indent":4,"parameters":[]},{"code":412,"indent":3,"parameters":[]},{"code":0,"indent":3,"parameters":[]},{"code":411,"indent":2,"parameters":[]},{"code":111,"indent":3,"parameters":[1,318,0,2,0]},{"code":111,"indent":4,"parameters":[1,310,0,15,1]},{"code":122,"indent":5,"parameters":[310,310,0,0,15]},{"code":122,"indent":5,"parameters":[318,318,0,0,3]},{"code":232,"indent":5,"parameters":[64,0,1,1,311,312,65,65,255,0,10,false]},{"code":0,"indent":5,"parameters":[]},{"code":412,"indent":4,"parameters":[]},{"code":0,"indent":4,"parameters":[]},{"code":411,"indent":3,"parameters":[]},{"code":111,"indent":4,"parameters":[1,318,0,1,0]},{"code":111,"indent":5,"parameters":[1,310,0,10,1]},{"code":122,"indent":6,"parameters":[310,310,0,0,10]},{"code":122,"indent":6,"parameters":[318,318,0,0,2]},{"code":232,"indent":6,"parameters":[64,0,1,1,311,312,50,50,255,0,10,false]},{"code":0,"indent":6,"parameters":[]},{"code":412,"indent":5,"parameters":[]},{"code":0,"indent":5,"parameters":[]},{"code":411,"indent":4,"parameters":[]},{"code":111,"indent":5,"parameters":[1,318,0,0,0]},{"code":111,"indent":6,"parameters":[1,310,0,5,1]},{"code":122,"indent":7,"parameters":[310,310,0,0,5]},{"code":122,"indent":7,"parameters":[318,318,0,0,1]},{"code":232,"indent":7,"parameters":[64,0,1,1,311,312,40,40,255,0,10,false]},{"code":0,"indent":7,"parameters":[]},{"code":412,"indent":6,"parameters":[]},{"code":0,"indent":6,"parameters":[]},{"code":412,"indent":5,"parameters":[]},{"code":0,"indent":5,"parameters":[]},{"code":412,"indent":4,"parameters":[]},{"code":0,"indent":4,"parameters":[]},{"code":412,"indent":3,"parameters":[]},{"code":0,"indent":3,"parameters":[]},{"code":412,"indent":2,"parameters":[]},{"code":0,"indent":2,"parameters":[]},{"code":412,"indent":1,"parameters":[]},{"code":0,"indent":1,"parameters":[]},{"code":412,"indent":0,"parameters":[]},{"code":0,"indent":0,"parameters":[]}],"moveFrequency":3,"moveRoute":{"list":[{"code":0,"parameters":[]}],"repeat":true,"skippable":false,"wait":false},"moveSpeed":3,"moveType":0,"priorityType":0,"stepAnime":false,"through":false,"trigger":4,"walkAnime":true},{"conditions":{"actorId":1,"actorValid":false,"itemId":1,"itemValid":false,"selfSwitchCh":"A","selfSwitchValid":false,"switch1Id":987,"switch1Valid":true,"switch2Id":1,"switch2Valid":false,"variableId":1,"variableValid":false,"variableValue":0},"directionFix":false,"image":{"characterIndex":0,"characterName":"","direction":2,"pattern":0,"tileId":0},"list":[{"code":0,"indent":0,"parameters":[]}],"moveFrequency":3,"moveRoute":{"list":[{"code":0,"parameters":[]}],"repeat":true,"skippable":false,"wait":false},"moveSpeed":3,"moveType":0,"priorityType":0,"stepAnime":false,"through":false,"trigger":0,"walkAnime":true},{"conditions":{"actorId":1,"actorValid":false,"itemId":1,"itemValid":false,"selfSwitchCh":"A","selfSwitchValid":false,"switch1Id":988,"switch1Valid":true,"switch2Id":1,"switch2Valid":false,"variableId":1,"variableValid":false,"variableValue":0},"directionFix":false,"image":{"characterIndex":0,"characterName":"","direction":2,"pattern":0,"tileId":0},"list":[{"code":0,"indent":0,"parameters":[]}],"moveFrequency":3,"moveRoute":{"list":[{"code":0,"parameters":[]}],"repeat":true,"skippable":false,"wait":false},"moveSpeed":3,"moveType":0,"priorityType":0,"stepAnime":false,"through":false,"trigger":0,"walkAnime":true}],"x":12,"y":2},{"id":8,"name":"EV008","note":"","pages":[{"conditions":{"actorId":1,"actorValid":false,"itemId":1,"itemValid":false,"selfSwitchCh":"A","selfSwitchValid":false,"switch1Id":986,"switch1Valid":true,"switch2Id":964,"switch2Valid":true,"variableId":1,"variableValid":false,"variableValue":0},"directionFix":false,"image":{"characterIndex":0,"characterName":"","direction":2,"pattern":0,"tileId":0},"list":[{"code":122,"indent":0,"parameters":[313,313,1,0,1]},{"code":230,"indent":0,"parameters":[10]},{"code":111,"indent":0,"parameters":[1,319,0,5,0]},{"code":111,"indent":1,"parameters":[1,313,0,30,2]},{"code":121,"indent":2,"parameters":[964,964,1]},{"code":122,"indent":2,"parameters":[313,313,0,0,0]},{"code":122,"indent":2,"parameters":[319,319,0,0,0]},{"code":250,"indent":2,"parameters":[{"name":"Damage3","volume":90,"pitch":100,"pan":0}]},{"code":224,"indent":2,"parameters":[[255,0,0,170],60,false]},{"code":235,"indent":2,"parameters":[65]},{"code":122,"indent":2,"parameters":[320,320,1,0,1]},{"code":0,"indent":2,"parameters":[]},{"code":412,"indent":1,"parameters":[]},{"code":0,"indent":1,"parameters":[]},{"code":411,"indent":0,"parameters":[]},{"code":111,"indent":1,"parameters":[1,319,0,4,0]},{"code":111,"indent":2,"parameters":[1,313,0,25,1]},{"code":122,"indent":3,"parameters":[313,313,0,0,25]},{"code":122,"indent":3,"parameters":[319,319,0,0,5]},{"code":232,"indent":3,"parameters":[65,0,1,1,314,315,100,100,255,0,10,false]},{"code":0,"indent":3,"parameters":[]},{"code":412,"indent":2,"parameters":[]},{"code":0,"indent":2,"parameters":[]},{"code":411,"indent":1,"parameters":[]},{"code":111,"indent":2,"parameters":[1,319,0,3,0]},{"code":111,"indent":3,"parameters":[1,313,0,20,1]},{"code":122,"indent":4,"parameters":[313,313,0,0,20]},{"code":122,"indent":4,"parameters":[319,319,0,0,4]},{"code":232,"indent":4,"parameters":[65,0,1,1,314,315,80,80,255,0,10,false]},{"code":0,"indent":4,"parameters":[]},{"code":412,"indent":3,"parameters":[]},{"code":0,"indent":3,"parameters":[]},{"code":411,"indent":2,"parameters":[]},{"code":111,"indent":3,"parameters":[1,319,0,2,0]},{"code":111,"indent":4,"parameters":[1,313,0,15,1]},{"code":122,"indent":5,"parameters":[313,313,0,0,15]},{"code":122,"indent":5,"parameters":[319,319,0,0,3]},{"code":232,"indent":5,"parameters":[65,0,1,1,314,315,65,65,255,0,10,false]},{"code":0,"indent":5,"parameters":[]},{"code":412,"indent":4,"parameters":[]},{"code":0,"indent":4,"parameters":[]},{"code":411,"indent":3,"parameters":[]},{"code":111,"indent":4,"parameters":[1,319,0,1,0]},{"code":111,"indent":5,"parameters":[1,313,0,10,1]},{"code":122,"indent":6,"parameters":[313,313,0,0,10]},{"code":122,"indent":6,"parameters":[319,319,0,0,2]},{"code":232,"indent":6,"parameters":[65,0,1,1,314,315,50,50,255,0,10,false]},{"code":0,"indent":6,"parameters":[]},{"code":412,"indent":5,"parameters":[]},{"code":0,"indent":5,"parameters":[]},{"code":411,"indent":4,"parameters":[]},{"code":111,"indent":5,"parameters":[1,319,0,0,0]},{"code":111,"indent":6,"parameters":[1,313,0,5,1]},{"code":122,"indent":7,"parameters":[313,313,0,0,5]},{"code":122,"indent":7,"parameters":[319,319,0,0,1]},{"code":232,"indent":7,"parameters":[65,0,1,1,314,315,40,40,255,0,10,false]},{"code":0,"indent":7,"parameters":[]},{"code":412,"indent":6,"parameters":[]},{"code":0,"indent":6,"parameters":[]},{"code":412,"indent":5,"parameters":[]},{"code":0,"indent":5,"parameters":[]},{"code":412,"indent":4,"parameters":[]},{"code":0,"indent":4,"parameters":[]},{"code":412,"indent":3,"parameters":[]},{"code":0,"indent":3,"parameters":[]},{"code":412,"indent":2,"parameters":[]},{"code":0,"indent":2,"parameters":[]},{"code":412,"indent":1,"parameters":[]},{"code":0,"indent":1,"parameters":[]},{"code":412,"indent":0,"parameters":[]},{"code":0,"indent":0,"parameters":[]}],"moveFrequency":3,"moveRoute":{"list":[{"code":0,"parameters":[]}],"repeat":true,"skippable":false,"wait":false},"moveSpeed":3,"moveType":0,"priorityType":0,"stepAnime":false,"through":false,"trigger":4,"walkAnime":true},{"conditions":{"actorId":1,"actorValid":false,"itemId":1,"itemValid":false,"selfSwitchCh":"A","selfSwitchValid":false,"switch1Id":987,"switch1Valid":true,"switch2Id":1,"switch2Valid":false,"variableId":1,"variableValid":false,"variableValue":0},"directionFix":false,"image":{"characterIndex":0,"characterName":"","direction":2,"pattern":0,"tileId":0},"list":[{"code":0,"indent":0,"parameters":[]}],"moveFrequency":3,"moveRoute":{"list":[{"code":0,"parameters":[]}],"repeat":true,"skippable":false,"wait":false},"moveSpeed":3,"moveType":0,"priorityType":0,"stepAnime":false,"through":false,"trigger":0,"walkAnime":true},{"conditions":{"actorId":1,"actorValid":false,"itemId":1,"itemValid":false,"selfSwitchCh":"A","selfSwitchValid":false,"switch1Id":988,"switch1Valid":true,"switch2Id":1,"switch2Valid":false,"variableId":1,"variableValid":false,"variableValue":0},"directionFix":false,"image":{"characterIndex":0,"characterName":"","direction":2,"pattern":0,"tileId":0},"list":[{"code":0,"indent":0,"parameters":[]}],"moveFrequency":3,"moveRoute":{"list":[{"code":0,"parameters":[]}],"repeat":true,"skippable":false,"wait":false},"moveSpeed":3,"moveType":0,"priorityType":0,"stepAnime":false,"through":false,"trigger":0,"walkAnime":true}],"x":12,"y":3},null,null,null,null,null,null,null,null,null,null,null,null,null,{"id":22,"name":"EV022","note":"","pages":[{"conditions":{"actorId":1,"actorValid":false,"itemId":1,"itemValid":false,"selfSwitchCh":"A","selfSwitchValid":false,"switch1Id":9,"switch1Valid":true,"switch2Id":1,"switch2Valid":false,"variableId":1,"variableValid":false,"variableValue":0},"directionFix":false,"image":{"characterIndex":0,"characterName":"","direction":2,"pattern":0,"tileId":0},"list":[{"code":122,"indent":0,"parameters":[10,10,0,4,"TouchInput._x;(TouchInput.x);"]},{"code":122,"indent":0,"parameters":[11,11,0,4,"TouchInput._y;(TouchInput.y);"]},{"code":111,"indent":0,"parameters":[12,"TouchInput.isTriggered()"]},{"code":356,"indent":1,"parameters":["Show_Animation \\v[10] \\v[11] 2"]},{"code":0,"indent":1,"parameters":[]},{"code":412,"indent":0,"parameters":[]},{"code":0,"indent":0,"parameters":[]}],"moveFrequency":3,"moveRoute":{"list":[{"code":0,"parameters":[]}],"repeat":true,"skippable":false,"wait":false},"moveSpeed":3,"moveType":0,"priorityType":0,"stepAnime":false,"through":false,"trigger":4,"walkAnime":true}],"x":16,"y":0},null]}